[
  {
    "raw_text": "Finish Ultimate vaatwastabletten\nAdvertentie\n15.49\n26 stuks"
  },
  {
    "raw_text": "Everdrop Allesreiniger starter set\nAdvertentie\n4.29\nper stuk"
  },
  {
    "raw_text": "AH Keukenpapier sterk & abs 2=3 rollen\n\n2 voor 4.99vanaf maandag\n\n3.19\n2 stuks"
  },
  {
    "raw_text": "AH Toiletpapier 4-laags 12=18 rollen\n8.89\n12 rollen\nKies\nLos\n2 Stuks"
  },
  {
    "raw_text": "Komo Trekbandzakken 60 liter\n1.99\n15 stuks"
  },
  {
    "raw_text": "Sun Brilliant shine plus vaatwascapsules\nAdvertentie\n\n2e gratisvanaf maandag\n\n17.79\n26 stuks"
  },
  {
    "raw_text": "Glorix original bleek\n\n4 voor 4.99vanaf maandag\n\n1.69\n0,75 l\nKies\nLos\n2 Stuks"
  },
  {
    "raw_text": "AH Tissues 2 lagen\n1.15\n150 stuks"
  },
  {
    "raw_text": "AH Vochtige allesreiniger doekjes citrus\n1.19\n80 stuks"
  },
  {
    "raw_text": "AH Keukenpapier sterk 3=6 rollen\n2.19\n3 stuks"
  },
  {
    "raw_text": "AH Tissues zacht & sterk\n1.15\n100 stuks"
  },
  {
    "raw_text": "AH Toiletpapier 4-laags 6=9 rollen\n4.55\n6 rollen"
  },
  {
    "raw_text": "Komo Huisvuilzakken 60 l\n2.09\n20 stuks"
  },
  {
    "raw_text": "AH Vochtige allesreiniger doekjes oceaan\n1.19\n80 stuks"
  },
  {
    "raw_text": "Glorix eucalyptus bleek\n\n4 voor 4.99vanaf maandag\n\n2.49\n0,75 l\nKies\nLos\n2 Stuks"
  },
  {
    "raw_text": "AH Toiletpapier 2-laags 16=24 rollen\n6.49\n16 rollen"
  },
  {
    "raw_text": "AH Aluminiumfolie\n2.39\n30 meter"
  },
  {
    "raw_text": "AH Dikke bleek\n0.89\n0,75 l"
  },
  {
    "raw_text": "Kleenex Balsam tissues\n2.29\n64 stuks"
  },
  {
    "raw_text": "AH Schoonmaakazijn\n0.69\n1 l"
  },
  {
    "raw_text": "AH Boterhamzakjes\n0.99\n80 stuks"
  },
  {
    "raw_text": "Page Aloe vera vochtig toiletpapier\n2.19\n38 stuks"
  },
  {
    "raw_text": "AH Vochtig toiletpapier fresh\n0.99\n80 stuks"
  },
  {
    "raw_text": "Page Sensitive vochtig toiletpapier\n2.09\n38 stuks"
  },
  {
    "raw_text": "AH Vochtige allesreiniger doekjes bloemen\n1.19\n80 stuks"
  },
  {
    "raw_text": "AH Classic vaatwastablet\n3.75\n60 stuks"
  },
  {
    "raw_text": "AH Wasmiddel kleur\n2.99\n25 wasbeurten"
  },
  {
    "raw_text": "Nalys Xtra power keukenpapier\n\n1 + 1 GRATISvandaag\n\n3.59\n2 rollen"
  },
  {
    "raw_text": "AH Power all in 1 vaatwastab citroen & munt\n3.49\n40 stuks"
  },
  {
    "raw_text": "AH Recycle toiletpapier 3laags 6=9 rollen\n3.99\n6 rollen"
  },
  {
    "raw_text": "AH Eco Afval en sanitairzakken 10 liter\n0.99\n10 stuks"
  },
  {
    "raw_text": "AH Pedaalemmerzakken 25 liter\n1.29\n50 stuks"
  },
  {
    "raw_text": "AH Treksluitzakken\n1.49\n15 stuks"
  },
  {
    "raw_text": "Page Compleet schoon vochtig toiletpapier\n1.99\n38 stuks"
  },
  {
    "raw_text": "Dreft Afwasmiddel max power original\n\n2e gratisvanaf maandag\n\n4.69\n450 ml\nKies\nLos\n3 Stuks"
  },
  {
    "raw_text": "AH Diepvrieszakjes met zipsluiting middel\n1.99\n40 stuks"
  },
  {
    "raw_text": "AH Eco Pedaalemmerzakken 20 liter\n2.69\n20 stuks\nKies\nLos\n2 Stuks"
  },
  {
    "raw_text": "AH Tissues extra zacht & sterk 4 lagen\n1.89\n80 stuks"
  },
  {
    "raw_text": "Tempo Original 4-laags zakdoeken\n2.45\n10 x 10 stuks"
  },
  {
    "raw_text": "AH Gedemineraliseerd water\n0.85\n1 l"
  },
  {
    "raw_text": "Multy Schuursponsen\n\nonline35% Op=Op kortingvanaf maandag\n\n1.29\n0.84\n10 stuks"
  },
  {
    "raw_text": "Kleenex Family maxi pack tissues\n3.19\n128 stuks"
  },
  {
    "raw_text": "Edet Ultra soft 4-laags toiletpapier\n\n1 + 1 GRATISvandaag\n\n6.39\n6 stuks"
  },
  {
    "raw_text": "AH Sanitairzakken met handvatten 10 liter\n1.29\n40 stuks\nKies\nLos\n4 Stuks"
  },
  {
    "raw_text": "AH Keukenpapier sterk & abs 4=6 rollen\n5.99\n4 stuks"
  },
  {
    "raw_text": "Edet Ultra soft toiletpapier stro voordeelpak\n\n1 + 1 GRATISvandaag\n\n16.99\n16 stuks"
  },
  {
    "raw_text": "AH Tissues balsem\n1.65\n150 stuks"
  },
  {
    "raw_text": "WC-Eend Wc eend nr. 1 ontkalker\n\n2e gratisvanaf maandag\n\n3.19\n0,75 l"
  },
  {
    "raw_text": "AH Schuurspons hard\n0.79\n6 stuks"
  },
  {
    "raw_text": "Page Shea butter vochtig toiletpapier\n2.19\n38 stuks"
  },
  {
    "raw_text": "Dreft Afwasmiddel platinum quick wash original\n\n2e gratisvanaf maandag\n\n2.99\n350 ml"
  },
  {
    "raw_text": "Mullrose Schoonmaakazijn\n3.45\n5 l"
  },
  {
    "raw_text": "Kleenex Collection tissues\n1.89\nPer stuk"
  },
  {
    "raw_text": "AH Spoelglans\n1.99\n1 l"
  },
  {
    "raw_text": "Ajax Allesreiniger eucalyptus\n3.49\n1,25 l\nKies\nLos\n2 Stuks"
  },
  {
    "raw_text": "Glorix WC blok power 5 met bleek\n\n2e gratisvanaf maandag\n\n4.19\nper stuk"
  },
  {
    "raw_text": "AH Afwasmiddel original\n0.89\n0,5 l"
  },
  {
    "raw_text": "AH Eco All in one vaatwastabletten\n3.79\n30 stuks"
  },
  {
    "raw_text": "Glorix Power5 citrus wc-blok\n\n2e gratisvanaf maandag\n\n3.85\nper stuk\nKies\nLos\n4 Stuks"
  },
  {
    "raw_text": "AH Trekbandzakken 120 liter\n1.69\n10 stuks"
  },
  {
    "raw_text": "AH Diepvrieszakjes met zipsluiting groot\n1.99\n30 stuks\nKies\nLos\n2 Stuks"
  },
  {
    "raw_text": "Edet Superior keukenpapier\n\n1 + 1 GRATISvandaag\n\n3.69\n2 stuks"
  },
  {
    "raw_text": "AH Viscosedoekjes\n1.99\n10 stuks"
  },
  {
    "raw_text": "AH Vuilnisemmerzakken 35L\n2.19\n20 stuks\nKies\nLos\n4 Stuks"
  },
  {
    "raw_text": "Tempo Original box 4-laags zakdoeken\n2.49\n100 stuks"
  },
  {
    "raw_text": "AH Aluminiumfolie extra dik\n\nonline35% Op=Op kortingvanaf maandag\n\n3.29\n2.14\n20 meter\nKies\nLos\n2 Stuks"
  },
  {
    "raw_text": "Robijn Klein & krachtig color wasmiddel\n16.19\n19 wasbeurten\nKies\nLos\n4 Stuks"
  },
  {
    "raw_text": "AH Wasmiddel kleur navulling\n5.49\n50 wasbeurten\nKies\nLos\n2 Stuks"
  },
  {
    "raw_text": "AH Afwasmiddel citrus\n0.89\n0,5 l"
  },
  {
    "raw_text": "Glorix Power5 ocean wc-blok\n\n2e gratisvanaf maandag\n\n3.95\nper stuk"
  },
  {
    "raw_text": "Witte Reus Toiletblok blauw actief hygiene\n\n60% kortingvandaag\n\n4.29\n1.72\n50 g\nKies\nLos\n5 Stuks"
  },
  {
    "raw_text": "AH Afwasborstel lang\n1.29\nper stuk"
  },
  {
    "raw_text": "Dreft Platinum plus deep clean vaatwascapsules\n\n2e gratisvanaf maandag\n\n13.99\n19 stuks"
  },
  {
    "raw_text": "Page Puur vochtig toiletpapier\n2.19\n38 stuks"
  },
  {
    "raw_text": "Nalys Vochtvangers keukenpapier 2=4 rol\n\n1 + 1 GRATISvandaag\n\n5.49\n2 stuks"
  },
  {
    "raw_text": "Glorix pink flower bleek\n\n4 voor 4.99vanaf maandag\n\n2.49\n0,75 l"
  },
  {
    "raw_text": "AH Keukenpapier sterk XXXL 1=8 rollen\n4.49\nper stuk"
  },
  {
    "raw_text": "Nalys Excellence 5-laags maxi-vel toiletpapier\n\n1 + 1 GRATISvandaag\n\n5.89\n6 stuks"
  },
  {
    "raw_text": "AH Eco Keukenpapier extra sterk 2=4 rollen\n2.99\n2 stuks"
  },
  {
    "raw_text": "Page Kussenzacht toiletpapier voordeelpak\n7.99\n12 stuks\nKies\nLos\n2 Stuks"
  },
  {
    "raw_text": "AH Vershoudfolie\n1.09\n50 meter"
  },
  {
    "raw_text": "Tricel Zilver soda\n1.39\n1 kg"
  },
  {
    "raw_text": "Driehoek Vloeibare zeep\n2.59\n0,73 l"
  },
  {
    "raw_text": "Sun All-in-one citroen vaatwastabletten\n\n2e gratisvanaf maandag\n\n9.99\n19 stuks"
  },
  {
    "raw_text": "Robijn Wasmiddel specials wol & fijn\n7.59\n18 wasbeurten"
  },
  {
    "raw_text": "Popla Megarol toiletpapier\n3.85\n4 rollen"
  },
  {
    "raw_text": "Glorix WC Blok Lavendel\n\n2e gratisvanaf maandag\n\n4.19\nper stuk"
  },
  {
    "raw_text": "Kleenex The original tissues\n2.19\n72 stuks"
  },
  {
    "raw_text": "AH Wasmiddel wit\n2.99\n25 wasbeurten"
  },
  {
    "raw_text": "Edet Easypull original navulling\n\n1 + 1 GRATISvandaag\n\n4.29\nper rol"
  },
  {
    "raw_text": "Glorix Pink magnolia blauw water wc-blok\n\n2e gratisvanaf maandag\n\n4.55\n55 g"
  },
  {
    "raw_text": "AH Toilet reinigingsdoekjes vochtig\n1.79\n40 stuks"
  },
  {
    "raw_text": "AH Glasspray\n1.69\n1 l"
  },
  {
    "raw_text": "Etos Brilpoetsdoekjes\n0.95\n30 stuks"
  },
  {
    "raw_text": "Edet Kamille vochtig toiletpapier\n\n1 + 1 GRATISvandaag\n\n2.79\n42 stuks"
  },
  {
    "raw_text": "Edet Amandelmelk vochtig toiletpapier\n\n1 + 1 GRATISvandaag\n\n2.79\n42 stuks"
  },
  {
    "raw_text": "Dettol Allesreiniger spray sprankelende citroen\n\n30% kortingvanaf maandag\n\n3.79\n2.65\n0,5 l"
  },
  {
    "raw_text": "Glorix Aroma lux dahila flower & dragonfruit\n\n2e gratisvanaf maandag\n\n4.19\nper stuk"
  },
  {
    "raw_text": "Klok Eco afwasmiddel\n1.39\n0,5 l"
  },
  {
    "raw_text": "AH Vochtig toiletpapier soft\n1.29\n40 stuks\nKies\nLos\n6 Stuks"
  },
  {
    "raw_text": "WC-Eend Wc eend action gel ocean\n\n2e gratisvanaf maandag\n\n3.75\n0,75 l"
  },
  {
    "raw_text": "AH Allesreiniger citrus spray\n1.99\n0,75 l"
  },
  {
    "raw_text": "Page Kussenzacht toiletpapier\n4.25\n6 stuks"
  },
  {
    "raw_text": "AH Latex handschoenen one size\n1.99\n20 stuks"
  },
  {
    "raw_text": "Dettol Antibacteriële schoonmaakdoekjes citroen\n\n30% kortingvanaf maandag\n\n4.49\n3.14\n72 stuks\nKies\nLos\n4 Stuks"
  },
  {
    "raw_text": "AH Pedaalemmerzakken met trekband 30 liter\n2.59\n25 stuks"
  },
  {
    "raw_text": "Dettol Allesreiniger spray linnen frisheid\n\n30% kortingvanaf maandag\n\n3.79\n2.65\n0,5 l\nKies\nLos\n3 Stuks"
  },
  {
    "raw_text": "Ajax Lentebloem allesreiniger\n3.19\n1 l"
  },
  {
    "raw_text": "Edet Limited edition vochtig toiletpapier\n\n1 + 1 GRATISvandaag\n\n2.79\n42 stuks"
  },
  {
    "raw_text": "Robijn Klein & krachtig stralend wit wasmiddel\n16.19\n19 wasbeurten\nKies\nLos\n4 Stuks"
  },
  {
    "raw_text": "Sun Shine & dry booster spoelglans\n\n2e gratisvanaf maandag\n\n5.49\n500 ml"
  },
  {
    "raw_text": "Nalys Wish keukenpapier\n\n1 + 1 GRATISvandaag\n\n4.99\n2 stuks"
  },
  {
    "raw_text": "Glassex Glas en multi schoonmaakspray\n3.29\n0,75 l"
  },
  {
    "raw_text": "Dreft Platinum+ deep clean vaatwastabletten\n\n2e gratisvanaf maandag\n\n24.99\n36 stuks\nKies\nLos\n4 Stuks"
  },
  {
    "raw_text": "AH Afwasborstel hout\n0.99\nper stuk"
  },
  {
    "raw_text": "Robijn Wasmiddeldoekjes color\n9.99\n16 wasbeurten"
  },
  {
    "raw_text": "Dreft Afwasmiddel max power citroen\n\n2e gratisvanaf maandag\n\n4.69\n450 ml"
  },
  {
    "raw_text": "Nalys Blitz huishoudrol\n\n1 + 1 GRATISvandaag\n\n4.29\nper stuk"
  },
  {
    "raw_text": "WC-Eend Fresh discs lime zest navul\n\n2e gratisvanaf maandag\n\n5.99\n72 ml"
  },
  {
    "raw_text": "Kleenex Balsam zakdoekjes\n2.29\n8 x 9 stuks"
  },
  {
    "raw_text": "Witte Reus Toiletblok deluxe delicate magnolia\n\n60% kortingvandaag\n\n4.29\n1.72\n50 g"
  },
  {
    "raw_text": "AH Keukenpapier extra sterk 3=4 rollen\n3.75\n3 stuks"
  },
  {
    "raw_text": "AH Wasmiddel zwart & donker\n2.99\n25 wasbeurten"
  },
  {
    "raw_text": "AH Wasverzachter geconcentreerd lentefris\n1.59\n30 wasbeurten"
  },
  {
    "raw_text": "Glorix WC blok wildberries\n\n2e gratisvanaf maandag\n\n4.19\nper stuk"
  },
  {
    "raw_text": "Marcel's Green Soap Toiletreiniger orange en jasmine\n3.79\n0,75 l"
  },
  {
    "raw_text": "AH Pedaalemmerzakken trekband lavendel 35l\n2.19\n15 stuks"
  },
  {
    "raw_text": "Cif Schuurmiddel citroen cream\n\n2e gratisvanaf maandag\n\n3.99\n0,75 l"
  },
  {
    "raw_text": "Ariel Vloeibaar+ color care wasmiddel\n\n1 + 1 GRATISvandaag\n\n15.99\n20 wasbeurten"
  },
  {
    "raw_text": "Broxomatic Vaatwasmachinezout\n1.19\n900 g"
  },
  {
    "raw_text": "Sun All-in-one citroen vaatwastabletten\n\n2e gratisvanaf maandag\n\n27.49\n60 stuks\nKies\nLos\n2 Stuks"
  },
  {
    "raw_text": "AH Puur vloeibaar wasmiddel kleur\n\n2e Halve Prijsvandaag\n\n4.99\n25 wasbeurten"
  },
  {
    "raw_text": "Page Vochtig compleet schoon maxi pack\n3.29\n74 stuks"
  },
  {
    "raw_text": "AH Vochtig toiletpapier alo vera\n1.29\n40 stuks"
  },
  {
    "raw_text": "Dettol Allesreiniger katoenfris\n\n30% kortingvanaf maandag\n\n3.99\n2.79\n1 l"
  },
  {
    "raw_text": "Ajax Allesreiniger fris\n2.49\n1,25 l"
  },
  {
    "raw_text": "Dreft Afwasmiddel platinum quick wash original\n\n2e gratisvanaf maandag\n\n4.39\n0,52 l"
  },
  {
    "raw_text": "Dettol Desinfecterende multi-oppervlakken spray\n\n30% kortingvanaf maandag\n\n3.79\n2.65\n0,5 l"
  },
  {
    "raw_text": "Glorix Power 5+ ocean wc-blok\n\n2e gratisvanaf maandag\n\n3.85\nper stuk"
  },
  {
    "raw_text": "Dreft Afwasmiddel platinum quick wash lemon\n\n2e gratisvanaf maandag\n\n2.99\n350 ml"
  },
  {
    "raw_text": "Antikal Original spray\n5.49\n0,8 l"
  },
  {
    "raw_text": "Sun Optimum machinereiniger\n\n2e gratisvanaf maandag\n\n4.99\n3 stuks"
  },
  {
    "raw_text": "AH Afwasborstel luxe\n1.99\nper stuk"
  },
  {
    "raw_text": "Dreft Afwasmiddel naturals pure lavendel\n\n2e gratisvanaf maandag\n\n3.99\n370 ml"
  },
  {
    "raw_text": "WC-Eend Wc eend action gel citrus\n\n2e gratisvanaf maandag\n\n3.75\n0,75 l"
  },
  {
    "raw_text": "AH Wasverzachter wilde rozen\n1.59\n30 wasbeurten"
  },
  {
    "raw_text": "Page Compleet schoon toiletpapier voordeelpak\n7.89\n12 stuks"
  },
  {
    "raw_text": "AH Afwasmiddel extra hygiëne\n0.99\n0,5 l"
  },
  {
    "raw_text": "AH Kleur beschermer doekjes\n1.79\n24 wasbeurten"
  },
  {
    "raw_text": "Glorix Aroma lux white rose & tea tree oil\n\n2e gratisvanaf maandag\n\n3.69\nper stuk"
  },
  {
    "raw_text": "Dettol Antibacteriële schoonmaakdoekjes citroen\n\n30% kortingvanaf maandag\n\n5.99\n4.19\n110 stuks"
  },
  {
    "raw_text": "Robijn Klein & krachtig black velvet wasmiddel\n16.19\n19 wasbeurten"
  },
  {
    "raw_text": "WC-Eend Fresh discs lime zest houder\n\n2e gratisvanaf maandag\n\n3.75\n36 ml"
  },
  {
    "raw_text": "Sun Brilliant shine all-in-1 vaatwascapsules\n\n2e gratisvanaf maandag\n\n9.99\n16 stuks"
  },
  {
    "raw_text": "WC-Eend Fresh discs mango-verse duo navulling\n\n2e gratisvanaf maandag\n\n5.99\n72 ml"
  },
  {
    "raw_text": "Dreft Platinum plus vaatwascapsules citroen\n\n2e gratisvanaf maandag\n\n13.99\n19 stuks"
  },
  {
    "raw_text": "Edet Natural skin balance\n\n1 + 1 GRATISvandaag\n\n2.85\n42 stuks"
  },
  {
    "raw_text": "AH Vloeibare vaatwas machinereiniger\n1.29\n250 ml"
  },
  {
    "raw_text": "Witte Reus Toiletblok deluxe lovely jasmin\n\n60% kortingvandaag\n\n4.29\n1.72\n50 g"
  },
  {
    "raw_text": "Ajax Rode bloemen allesreiniger\n3.29\n1 l"
  },
  {
    "raw_text": "AH Afwasborstel met zuignap\n1.59\nper stuk"
  },
  {
    "raw_text": "Nalys Vochtvangers mega pack\n\n1 + 1 GRATISvandaag\n\n11.29\n7.34\n8 stuks"
  },
  {
    "raw_text": "Swiffer Duster navulling\n9.99\n7 stuks"
  },
  {
    "raw_text": "WC-Eend Wc eend action gel pine\n\n2e gratisvanaf maandag\n\n3.75\n0,75 l"
  },
  {
    "raw_text": "Lenor Geurbooster zeebries\n\n3 VOOR 14.99vandaag\n\n11.99\n235 g\nKies\nLos\n4 Stuks"
  },
  {
    "raw_text": "AH Wascapsules 3-in-1 kleur\n5.09\n24 wasbeurten"
  },
  {
    "raw_text": "Swirl Afvalzakken fixeerband 30 liter\n3.65\n10 stuks"
  },
  {
    "raw_text": "HG Vloeibare ontstopper\n7.09\n1 l"
  },
  {
    "raw_text": "AH Power all in 1 vaatwastabletten\n6.45\n75 stuks"
  },
  {
    "raw_text": "AH Eco Toiletreiniger citroen\n1.45\n0,75 l"
  },
  {
    "raw_text": "AH Allesreiniger bloemen & fruit spray\n1.99\n0,75 l"
  },
  {
    "raw_text": "AH Huishoudhandschoenen large\n0.79\nper paar"
  },
  {
    "raw_text": "AH Eco Toiletreiniger dennen\n1.45\n0,75 l"
  },
  {
    "raw_text": "AH Schuurspons zacht\n0.99\n3 stuks"
  },
  {
    "raw_text": "Kleenex Ultra soft tissues\n2.39\n64 stuks"
  },
  {
    "raw_text": "Robijn Color wasmiddel voordeelfles\n28.69\n39 wasbeurten\nKies\nLos\n4 Stuks"
  },
  {
    "raw_text": "Sun All-in-one normaal vaatwastabletten\n\n2e gratisvanaf maandag\n\n9.99\n19 stuks"
  },
  {
    "raw_text": "Robijn Wasverzachter morgenfris\n8.69\n50 wasbeurten"
  },
  {
    "raw_text": "Shout Vlekkenspray\n3.79\n0,5 l"
  },
  {
    "raw_text": "Ariel 4-in-1 pods+ unstoppables wascapsules\n\n1 + 1 GRATISvandaag\n\n26.49\n26 wasbeurten"
  },
  {
    "raw_text": "AH Eco Allesreiniger citroen\n1.45\n1,25 l"
  },
  {
    "raw_text": "Witte Reus Toiletblok kracht actief oceaan\n\n60% kortingvandaag\n\n6.99\n2.80\n100 g"
  },
  {
    "raw_text": "AH Schuurmiddel citroen\n1.19\n0,75 l"
  },
  {
    "raw_text": "Sun Classic vaatwaspoeder\n9.99\n1,36 kg"
  },
  {
    "raw_text": "AH Trekbandzak pmd 60 liter\n1.19\n10 stuks"
  },
  {
    "raw_text": "Dreft Platinum vaatwastabletten regular\n\n2e gratisvanaf maandag\n\n20.39\n39 stuks\nKies\nLos\n4 Stuks"
  },
  {
    "raw_text": "Tempo Natural & soft box 4-laags zakdoeken\n2.49\n90 st"
  },
  {
    "raw_text": "Marcel's Green Soap Hygienische doekjes patchouli&cranberry\n3.59\n60 stuks"
  },
  {
    "raw_text": "Robijn Wasparfum tropical\n6.99\n342 ml"
  },
  {
    "raw_text": "Fleuril Renew color & fiber vloeibaar wasmiddel\n\n1 + 1 GRATISvandaag\n\n13.99\n29 wasbeurten"
  },
  {
    "raw_text": "Sun Brilliant shine all-in-1 vaatwascapsules\n\n2e gratisvanaf maandag\n\n19.59\n34 stuks"
  },
  {
    "raw_text": "Robijn 3-in-1 Wascapsules color\n10.29\n15 wasbeurten"
  },
  {
    "raw_text": "AH Zeemineralen & cederhout luchtverfrisser\n1.99\n250 ml"
  },
  {
    "raw_text": "Color Reus Wasmiddel vloeibaar gel kleur\n\n1 + 1 GRATISvandaag\n\n9.29\n19 wasbeurten\nKies\nLos\n4 Stuks"
  },
  {
    "raw_text": "Dubro Multi ontvetterspray\n3.99\n0,65 l"
  },
  {
    "raw_text": "Mr Muscle Power gel ontstopper\n5.29\n1 l"
  },
  {
    "raw_text": "AH Keukenpapier recycled 3-laags\n3.99\n3 rollen"
  },
  {
    "raw_text": "Ajax 100% hygiene schoonmaakdoekjes\n3.79\n100 stuks"
  },
  {
    "raw_text": "Sun Vaatwasmachine verfrisser citroen\n\n2e gratisvanaf maandag\n\n4.49\nper stuk"
  },
  {
    "raw_text": "AH Power all in 1 vaatwascapsules citroen\n4.29\n25 stuks"
  },
  {
    "raw_text": "Finish Quantum vaatwastabletten\n20.59\n44 stuks"
  },
  {
    "raw_text": "Lenor Light geurbooster katoen fris\n\n3 VOOR 14.99vandaag\n\n11.99\n235 g"
  },
  {
    "raw_text": "Mr Muscle Keukenreiniger spray\n3.59\n0,5 l"
  },
  {
    "raw_text": "Robijn Wasparfum spa sensation\n6.99\n342 ml"
  },
  {
    "raw_text": "WC-Eend Fresh discs coloring bluing navulling\n\n2e gratisvanaf maandag\n\n6.65\n72 ml"
  },
  {
    "raw_text": "Robijn Wasparfum paradise secret\n6.99\n342 ml"
  },
  {
    "raw_text": "AH Wasverzachter geconcentreerd fris\n2.19\n80 wasbeurten"
  },
  {
    "raw_text": "Page Kussenzacht toiletpapier voordeelpak\n15.89\n24 stuks"
  },
  {
    "raw_text": "Lenor Geurbooster gouden orchidee\n\n3 VOOR 14.99vandaag\n\n11.99\n235 g\nKies\nLos\n4 Stuks"
  },
  {
    "raw_text": "AH Wasmiddel kleur rozen & zomerfruit\n3.99\n25 wasbeurten"
  },
  {
    "raw_text": "Page Sensitive vochtig toiletpapier\n3.29\n74 stuks"
  },
  {
    "raw_text": "AH Jasmijn & citrus luchtverfrisser\n1.99\n250 ml"
  },
  {
    "raw_text": "Witte Reus Toiletblok kracht actief munt eucalyptus\n\n60% kortingvandaag\n\n3.69\n1.48\n50 g"
  },
  {
    "raw_text": "Swirl Pedaalemmerzakken ocean 5 liter\n2.99\n45 stuks"
  },
  {
    "raw_text": "Marcel's Green Soap Allesreiniger sandalwood cardamon spray\n3.49\n0,5 l"
  },
  {
    "raw_text": "AH Eco Wasmiddel puur kleur poeder\n\n2e Halve Prijsvandaag\n\n4.89\n20 wasbeurten"
  },
  {
    "raw_text": "HG Schimmel, vocht & weerplekkenreiniger\n9.99\n0,5 l"
  },
  {
    "raw_text": "AH 3-in-1 Folie\n1.85\n20 meter"
  },
  {
    "raw_text": "Tempo Complete care 4-laags zakdoeken\n3.09\n10 x 9 stuks"
  },
  {
    "raw_text": "Neutral Wasmiddel colour sensitive skin\n\n2e Halve Prijsvandaag\n\n8.69\n20 wasbeurten"
  },
  {
    "raw_text": "Marcel's Green Soap Vaatwastabletten alles-in-een\n9.99\n25 stuks"
  },
  {
    "raw_text": "AH Wasmiddel wol & fijn\n3.99\n25 wasbeurten"
  },
  {
    "raw_text": "Toppits Bakvellen\n3.99\n16 stuks"
  },
  {
    "raw_text": "Biotex Waspoeder handwas & inweek\n5.99\n720 g"
  },
  {
    "raw_text": "Andy Allesreiniger lotus & acacia\n\n2e gratisvanaf maandag\n\n2.99\n1 l"
  },
  {
    "raw_text": "AH Huishouddoekje\n0.95\n6 stuks"
  },
  {
    "raw_text": "Ariel Color family pack XL wasmiddel\n\n2e gratisvanaf maandag\n\n29.29\n46 wasbeurten"
  },
  {
    "raw_text": "AH Zakdoekjes balsem\n2.39\n150 stuks"
  },
  {
    "raw_text": "Witte Reus Toiletblok kracht actief lavendel\n\n60% kortingvandaag\n\n3.69\n1.48\n50 g"
  },
  {
    "raw_text": "WC-Eend Fresh discs mango-verse houder\n\n2e gratisvanaf maandag\n\n3.75\n36 ml"
  },
  {
    "raw_text": "Marcel's Green Soap Keukenreiniger orange jasmin\n3.49\n0,5 l"
  },
  {
    "raw_text": "Sun Brilliant shine all-in-1 vaatwascapsules\n\n2e gratisvanaf maandag\n\n14.99\n26 stuks"
  },
  {
    "raw_text": "Dreft Platinum plus vaatwastabletten citroen\n\n2e gratisvanaf maandag\n\n24.99\n36 stuks\nKies\nLos\n4 Stuks"
  },
  {
    "raw_text": "Dreft 3 in 1 power lemon spray\n\n2e gratisvanaf maandag\n\n7.99\n0,5 l"
  },
  {
    "raw_text": "Dettol Allesreiniger sprankelende citroen\n\n30% kortingvanaf maandag\n\n3.99\n2.79\n1 l"
  },
  {
    "raw_text": "Ajax Shower power spray\n3.49\n0,75 l"
  },
  {
    "raw_text": "AH Luchtverfrisser ocean\n0.85\n250 ml"
  },
  {
    "raw_text": "AH Kalkreiniger spray\n2.19\n0,75 l"
  },
  {
    "raw_text": "Finish Integrale machinereiniger\n4.89\n250 ml"
  },
  {
    "raw_text": "Blue Wonder Disinfect & cleaning wipes\n4.75\n72 stuks"
  },
  {
    "raw_text": "Edet Easypull premium navulling\n\n1 + 1 GRATISvandaag\n\n4.29\nper rol"
  },
  {
    "raw_text": "AH Wasmiddel wit navulling\n5.49\n50 wasbeurten"
  },
  {
    "raw_text": "Lenor Unstoppables geurbooster fris\n\n3 VOOR 14.99vandaag\n\n11.99\n235 g"
  },
  {
    "raw_text": "AH Luchtverfrisser bloemen\n0.85\n250 ml"
  },
  {
    "raw_text": "AH Pannenspons roestvrijstaal\n0.69\n2 stuks"
  },
  {
    "raw_text": "Witte Reus Toiletblok turquoise actief pacific\n\n60% kortingvandaag\n\n4.29\n1.72\n50 g"
  },
  {
    "raw_text": "AH Wasmiddel zwart & donker navulling\n5.49\n50 wasbeurten\nKies\nLos\n2 Stuks"
  },
  {
    "raw_text": "AH Microvezeldoekjes\n2.49\n3 stuks"
  },
  {
    "raw_text": "HG Kookplaatreiniger\n5.79\n0,5 l"
  },
  {
    "raw_text": "Ariel 3-in-1 pods color wasmiddelcapsules\n\n1 + 1 GRATISvandaag\n\n12.99\n15 wasbeurten\nKies\nLos\n4 Stuks"
  },
  {
    "raw_text": "Dettol Schoonmaakdoekjes oceaanfris\n\n30% kortingvanaf maandag\n\n5.99\n4.19\n110 stuks"
  },
  {
    "raw_text": "AH Power toiletblokken citrus\n1.99\n2 stuks"
  },
  {
    "raw_text": "Page Toiletpapier kussenzacht design\n2.99\n4 stuks"
  },
  {
    "raw_text": "Swirl Vuilniszakken met fixeerband 35 liter\n3.65\n10 stuks"
  },
  {
    "raw_text": "Cif Schuurmiddel original cream\n\n2e gratisvanaf maandag\n\n3.99\n0,75 l"
  },
  {
    "raw_text": "Ajax Limoen allesreiniger\n3.49\n1,25 l"
  },
  {
    "raw_text": "Destop Ontstopper turbo\n4.29\n0,5 l"
  },
  {
    "raw_text": "AH Toiletblok frisse oceaanbries\n0.99\nper stuk"
  },
  {
    "raw_text": "Ariel 3-in-1 pods color wasmiddelcapsules\n\n1 + 1 GRATISvandaag\n\n22.99\n30 wasbeurten"
  },
  {
    "raw_text": "Ariel Vloeibaar original\n\n2e gratisvanaf maandag\n\n13.99\n20 wasbeurten"
  },
  {
    "raw_text": "AH Vloeibare zeep\n1.39\n0,75 l"
  },
  {
    "raw_text": "AH Geureditie ververser rozen & zomerfris\n1.99\n250 ml"
  },
  {
    "raw_text": "Witte Reus Wellness scents harmony wc-blok\n\n60% kortingvandaag\n\n4.29\n1.72\n50 g"
  },
  {
    "raw_text": "Sun In-wash vaatwasmachinereiniger\n\n2e gratisvanaf maandag\n\n5.99\n60 g"
  },
  {
    "raw_text": "Swirl Pedaalemmerzak anti-geur 20 liter\n2.99\n12 stuks"
  },
  {
    "raw_text": "Ariel Revita black+ wasmiddel\n\n1 + 1 GRATISvandaag\n\n15.99\n20 wasbeurten"
  },
  {
    "raw_text": "Robijn Wascapsules color\n17.79\n26 wasbeurten\nKies\nLos\n4 Stuks"
  },
  {
    "raw_text": "Dettol Allesreiniger spray badkamer\n\n30% kortingvanaf maandag\n\n3.89\n2.72\n0,5 l"
  },
  {
    "raw_text": "Robijn Wasmiddeldoekjes stralend wit\n9.99\n16 wasbeurten"
  },
  {
    "raw_text": "AH Wasverzachter geconcentreerd lavendel\n1.59\n30 wasbeurten"
  },
  {
    "raw_text": "AH Toiletblok lavendel\n0.99\n40 g"
  },
  {
    "raw_text": "HG Schimmelreiniger schuimspray\n11.29\n0,5 l"
  },
  {
    "raw_text": "Marcel's Green Soap Hygienische doekjes sandalwood\n3.59\n60 stuks"
  },
  {
    "raw_text": "Marcel's Green Soap Toiletblok mint ecalyptus\n3.49\nper stuk"
  },
  {
    "raw_text": "Glade Langdurig lavender gel\n\n40% kortingvanaf maandag\n\n1.65\n0.99\n150 g"
  },
  {
    "raw_text": "AH Brandspiritus 85%\n2.49\n1 l"
  },
  {
    "raw_text": "Toppits Vershoudfolie\n1.99\n20 meter"
  },
  {
    "raw_text": "Robijn Wasmiddeldoekjes black\n9.99\n16 wasbeurten"
  },
  {
    "raw_text": "AH Wasverzachter geconcentreerd puur\n\n2e Halve Prijsvandaag\n\n1.59\n30 wasbeurten"
  },
  {
    "raw_text": "Dubro Badkamerreiniger spray\n3.99\n0,65 l"
  },
  {
    "raw_text": "AH Wasmiddel kleur zeemineralen & cederhout\n3.99\n25 wasbeurten"
  },
  {
    "raw_text": "AH Allesreiniger bloemen & fruit navulling\n\n2 VOOR 3.50vandaag\n\n1.89\n0,75 l\nKies\nLos\n2 Stuks"
  },
  {
    "raw_text": "Robijn Wasverzachter puur & zacht\n\n3 voor 9.00vanaf maandag\n\n6.79\n39 wasbeurten"
  },
  {
    "raw_text": "Glade Langdurig relaxing zen gel\n\n40% kortingvanaf maandag\n\n1.65\n0.99\n150 g"
  },
  {
    "raw_text": "Ajax Rode hibiscus allesreiniger\n3.59\n1 l"
  },
  {
    "raw_text": "Tempo Light box 3-laags zakdoeken\n1.69\n70 stuks"
  },
  {
    "raw_text": "Dettol Schoonmaakdoekjes cleanser\n\n30% kortingvanaf maandag\n\n4.49\n3.14\n72 stuks"
  },
  {
    "raw_text": "AH Wasmiddel kleur jasmijn & citrus\n3.99\n25 wasbeurten"
  },
  {
    "raw_text": "Robijn Color paradise secret wasmiddel\n18.39\n19 wasbeurten"
  },
  {
    "raw_text": "Vanish Vlekverwijderaar spray\n\n50% kortingvandaag\n\n7.99\n3.99\n0,5 l"
  },
  {
    "raw_text": "Marcel's Green Soap Allesreiniger orange jasmine\n3.49\n0,75 l"
  },
  {
    "raw_text": "AH Wasverzachter jasmijn & citrus\n1.99\n30 wasbeurten"
  },
  {
    "raw_text": "Driehoek Kristal soda\n2.59\n600 g"
  },
  {
    "raw_text": "Fleuril Renew black & fiber vloeibaar wasmiddel\n\n1 + 1 GRATISvandaag\n\n13.99\n29 wasbeurten"
  },
  {
    "raw_text": "Ariel Active+ wasmiddel\n\n1 + 1 GRATISvandaag\n\n15.99\n20 wasbeurten"
  },
  {
    "raw_text": "Biotex Wasmiddel waskrachtversterker waspoeder\n5.99\n720 g"
  },
  {
    "raw_text": "Dubro Keuken ontvetterspray\n3.99\n0,65 l"
  },
  {
    "raw_text": "Marcel's Green Soap Badkamerreiniger patchouli cranberry\n3.49\n0,5 l"
  },
  {
    "raw_text": "Lenor Fresh air wasverzachter ochtendfris\n\n3 VOOR 14.99vandaag\n\n8.19\n36 wasbeurten"
  },
  {
    "raw_text": "Marcel's Green Soap Toiletblok lemon ginger\n3.49\nper stuk"
  },
  {
    "raw_text": "AH Hersluitbare zakjes\n2.45\n50 stuks"
  },
  {
    "raw_text": "Finish Glansspoelmiddel\n4.29\n400 ml"
  },
  {
    "raw_text": "Dubro Hygiëne ontvetter doekjes eucalyptus\n4.99\n80 stuks"
  },
  {
    "raw_text": "Robijn Wasverzachter morgenfris\n\n3 voor 9.00vanaf maandag\n\n6.79\n39 wasbeurten"
  },
  {
    "raw_text": "AH Vochtige XL vloerdoeken\n2.09\n15 stuks\nKies\nLos\n3 Stuks"
  },
  {
    "raw_text": "Swirl Afvalzakken fixeerband 20 liter\n3.65\n15 stuks"
  },
  {
    "raw_text": "AH Hersluitbare zakjes 0.4liter + 1.2liter\n1.99\n60 stuks"
  },
  {
    "raw_text": "AH Power toiletblokken oceaan\n1.99\n2 stuks"
  },
  {
    "raw_text": "Robijn Intense morgenfris geurbuiltjes\n3.99\n3 wasbeurten"
  },
  {
    "raw_text": "Edet Keukenpapier\n\n1 + 1 GRATISvandaag\n\n11.89\n8 stuks"
  },
  {
    "raw_text": "Lenor Light geurbooster zijdebloesem en pioen\n\n3 VOOR 14.99vandaag\n\n11.99\n235 g"
  },
  {
    "raw_text": "AH Afwasmiddel dermatologisch\n0.99\n0,5 l"
  },
  {
    "raw_text": "Seepje Afwasmiddel tintelfrisse limoen geur\n\n2e gratisvanaf maandag\n\n3.29\n0,5 l"
  },
  {
    "raw_text": "Robijn Color tropical wasmiddel\n18.39\n19 wasbeurten"
  },
  {
    "raw_text": "Swirl Vuilniszakken met fixeerband 60 liter\n3.69\n10 stuks"
  },
  {
    "raw_text": "Marcel's Green Soap Allesreiniger lavender & rosemary\n3.49\n0,5 l"
  },
  {
    "raw_text": "AH Sanitairspons met zeem\n0.89\nper stuk"
  },
  {
    "raw_text": "Robijn Color zwitsal wasmiddel\n18.39\n19 wasbeurten"
  },
  {
    "raw_text": "Robijn Collections capsules paradise secret\n14.15\n15 wasbeurten"
  },
  {
    "raw_text": "Blue Wonder Desinfectie reiniger spray\n5.09\n0,75 l"
  },
  {
    "raw_text": "Swirl Pedaalemmerzak anti-geur 35 liter\n3.29\n9 stuks"
  },
  {
    "raw_text": "Nalys Soft bamboo 4=8 rol\n\n1 + 1 GRATISvandaag\n\n6.49\n4 rollen"
  },
  {
    "raw_text": "Toppits Super alufolie\n3.99\n10 meter"
  },
  {
    "raw_text": "Cif Schuurmiddel pink flower cream\n\n2e gratisvanaf maandag\n\n3.99\n0,75 l"
  },
  {
    "raw_text": "AH Allesreiniger citrus navulling\n\n2 VOOR 3.50vandaag\n\n1.89\n0,75 l"
  },
  {
    "raw_text": "Lenor Geurparels robijn jasmijn\n\n3 VOOR 14.99vandaag\n\n11.99\n235 g"
  },
  {
    "raw_text": "Robijn Color pink sensation wasmiddel\n17.49\n19 wasbeurten"
  },
  {
    "raw_text": "Ajax Blauwe jasmijn allesreiniger\n3.59\n1 l"
  },
  {
    "raw_text": "Edet Comfort plus toiletpapier met stro\n\n1 + 1 GRATISvandaag\n\n6.39\n6 stuks"
  },
  {
    "raw_text": "Robijn Droogtrommeldoekjes morgenfris\n3.99\n20 wasbeurten"
  },
  {
    "raw_text": "Neutral Parfumvrij waspoeder kleur\n\n2e Halve Prijsvandaag\n\n7.99\n18 wasbeurten"
  },
  {
    "raw_text": "Dreft Afwasmiddel platinum quick wash original\n\n2e gratisvanaf maandag\n\n6.49\n0,78 l"
  },
  {
    "raw_text": "AH Wasverzachter zacht & fris\n1.59\n30 wasbeurten"
  },
  {
    "raw_text": "Ecover Wc-reiniger den & munt\n\n2e gratisvanaf maandag\n\n3.89\n0,75 l"
  },
  {
    "raw_text": "Finish Machinereiniger tijdens de wasbeurt\n5.99\n3 stuks"
  },
  {
    "raw_text": "AH Ijsblokzakjes\n0.59\n10 stuks"
  },
  {
    "raw_text": "Finish Verfrisser citroen\n3.49\nper stuk"
  },
  {
    "raw_text": "Ecover Allesreiniger citroengras & gember\n\n2e gratisvanaf maandag\n\n3.49\n1 l"
  },
  {
    "raw_text": "Nalys Toiletpapier soft mega pack\n\n1 + 1 GRATISvandaag\n\n15.99\n24 stuks"
  },
  {
    "raw_text": "HG Tegen nare geur in sportkleding\n7.29\n500 g"
  },
  {
    "raw_text": "Dettol Allesreiniger spray keuken\n\n30% kortingvanaf maandag\n\n3.89\n2.72\n0,5 l"
  },
  {
    "raw_text": "AH Puur vloeibaar wasmiddel wit\n\n2e Halve Prijsvandaag\n\n4.99\n25 wasbeurten"
  },
  {
    "raw_text": "Robijn Fleur & fijn waspoeder kleur\n5.29\n10 wasbeurten"
  },
  {
    "raw_text": "Dr. Beckmann Wasmachine hygiene reiniger\n3.99\n250 g"
  },
  {
    "raw_text": "Toppits Lunchzakjes\n3.19\n50 stuks"
  },
  {
    "raw_text": "Robijn Stralend wit wasmiddel voordeelfles\n28.69\n39 wasbeurten"
  },
  {
    "raw_text": "Ecover All-in-one vaatwastabletten\n\n2e gratisvanaf maandag\n\n9.99\n24 stuks"
  },
  {
    "raw_text": "Dubro Afwasmiddel orginal extra citroen\n2.99\n550 ml"
  },
  {
    "raw_text": "AH Keukenreiniger spray navulling\n\n2 VOOR 3.50vandaag\n\n1.99\n0,75 l\nKies\nLos\n2 Stuks"
  },
  {
    "raw_text": "AH Containerzakken 240 liter\n1.79\n10 stuks"
  },
  {
    "raw_text": "Ajax Plant based schoonmaakdoekjes\n3.79\n100 stuks"
  },
  {
    "raw_text": "Driehoek Vloeibare soda\n2.59\n0,73 l"
  },
  {
    "raw_text": "Nalys Eindeloos toiletpapier 2-laags 4=15 rol\n\n1 + 1 GRATISvandaag\n\n6.99\n4 rollen"
  },
  {
    "raw_text": "AH Kalkreiniger spray navulling\n\n2 VOOR 3.50vandaag\n\n1.99\n0,75 l\nKies\nLos\n2 Stuks"
  },
  {
    "raw_text": "Edet Comfort plus luchtverfrisser 6=9 rol\n\n1 + 1 GRATISvandaag\n\n6.59\n6 rollen"
  },
  {
    "raw_text": "Edet Superior keukenpapier voordeelpak\n\n1 + 1 GRATISvandaag\n\n10.99\n6 stuks"
  },
  {
    "raw_text": "Glade Luchtverfrisser spray relaxing zen\n\n40% kortingvanaf maandag\n\n2.15\n1.29\n300 ml"
  },
  {
    "raw_text": "AH Luchtverfrisser lavendel\n0.85\n250 ml"
  },
  {
    "raw_text": "Witte Reus Kracht actief bloesem\n\n60% kortingvandaag\n\n3.69\n1.48\n50 g"
  },
  {
    "raw_text": "Sun All-in-one citroen vaatwastabletten\n\n2e gratisvanaf maandag\n\n21.49\n46 stuks"
  },
  {
    "raw_text": "Edet Comfort plus toiletpapier stro voordeel\n\n1 + 1 GRATISvandaag\n\n16.99\n16 rollen"
  },
  {
    "raw_text": "Robijn Black beautiful mystery wasmiddel\n18.39\n19 wasbeurten"
  },
  {
    "raw_text": "Marcel's Green Soap Afwasmiddel orange jasmine\n3.29\n0,5 l"
  },
  {
    "raw_text": "Dr. Beckmann Pre Wash spray\n3.79\n0,5 l"
  },
  {
    "raw_text": "Robijn Color spa sensation wasmiddel\n18.39\n19 wasbeurten"
  },
  {
    "raw_text": "Marcel's Green Soap Wasmiddel vanilla & cotton navulling\n\n2e Halve Prijsvandaag\n\n9.79\n23 wasbeurten"
  },
  {
    "raw_text": "AH Badkamerreiniger spray navulling\n\n2 VOOR 3.50vandaag\n\n1.99\n0,75 l"
  },
  {
    "raw_text": "Tempo Soft & sensitive\n2.49\n8 x 9 stuks"
  },
  {
    "raw_text": "Ariel Color+ touch of lenor wasmiddel\n\n1 + 1 GRATISvandaag\n\n15.99\n20 wasbeurten\nKies\nLos\n3 Stuks"
  },
  {
    "raw_text": "Driehoek Zachte Zeep\n4.29\n900 g"
  },
  {
    "raw_text": "Ariel 3-in-1 pods original wasmiddelcapsules\n\n1 + 1 GRATISvandaag\n\n12.99\n15 wasbeurten"
  },
  {
    "raw_text": "Fleuril Renew bloesem vloeibaar wasmiddel\n\n1 + 1 GRATISvandaag\n\n14.99\n29 wasbeurten"
  },
  {
    "raw_text": "Ariel 3-in-1 pods original wasmiddelcapsules\n\n1 + 1 GRATISvandaag\n\n22.99\n30 wasbeurten"
  },
  {
    "raw_text": "HG Mierenlokdoos binnen/buiten\n8.79\n2 stuks"
  },
  {
    "raw_text": "Ariel 4in1 pods+ active wasmiddelcapsules\n\n1 + 1 GRATISvandaag\n\n26.49\n26 wasbeurten"
  },
  {
    "raw_text": "Dreft Platinum plus vaatwascapsules quick wash\n\n2e gratisvanaf maandag\n\n13.99\n19 stuks"
  },
  {
    "raw_text": "HG Kalkweg schuimspray 3x sterker\n7.79\n0,5 l"
  },
  {
    "raw_text": "Robijn Black velvet wasmiddel voordeelfles\n28.69\n39 wasbeurten"
  },
  {
    "raw_text": "Ariel Vloeibaar color\n\n2e gratisvanaf maandag\n\n13.99\n20 wasbeurten\nKies\nLos\n3 Stuks"
  },
  {
    "raw_text": "Swirl Vuilniszakken met trekband 60 liter\n2.99\n10 stuks"
  },
  {
    "raw_text": "Finish Ultimate Plus vaatwastabletten\n15.49\n22 stuks"
  },
  {
    "raw_text": "Dreft Platinum original vaatwastabletten XXL\n\n2e gratisvanaf maandag\n\n29.99\n66 stuks"
  },
  {
    "raw_text": "Toppits Zipper\n3.49\n12 stuks"
  },
  {
    "raw_text": "AH Eco Wasmiddel puur wit poeder\n\n2e Halve Prijsvandaag\n\n4.89\n20 wasbeurten"
  },
  {
    "raw_text": "Ariel 4in1 pods+ ultra wasmiddelcapsules\n\n1 + 1 GRATISvandaag\n\n15.99\n15 wasbeurten"
  },
  {
    "raw_text": "Witte Reus Wasmiddel vloeibaar gel wit\n\n1 + 1 GRATISvandaag\n\n9.29\n19 wasbeurten\nKies\nLos\n4 Stuks"
  },
  {
    "raw_text": "Vanish Powergel vlekverwijderaar\n\n50% kortingvandaag\n\n5.25\n2.62\n200 ml"
  },
  {
    "raw_text": "Driehoek Vloeibare zeep oranje bloesem\n2.59\n0,73 l"
  },
  {
    "raw_text": "Tempo Natural & soft 4-laags zakdoeken\n2.49\n72 stuks"
  },
  {
    "raw_text": "Marcel's Green Soap Afwasmiddel orange jasmine navulling\n2.99\n0,5 l"
  },
  {
    "raw_text": "AH Wasmiddel kleur lavendel & kamille\n3.99\n25 wasbeurten"
  },
  {
    "raw_text": "AH Keukenreiniger spray\n2.19\n0,75 l"
  },
  {
    "raw_text": "Neutral Parfumvrij wasverzachter\n\n2e Halve Prijsvandaag\n\n4.45\n27 wasbeurten"
  },
  {
    "raw_text": "Mr Muscle Ovenreiniger spray\n3.79\n300 ml"
  },
  {
    "raw_text": "AH Toilet reinigingstabletten\n3.49\n16 stuks"
  },
  {
    "raw_text": "Finish Ultimate plus vaatwastabletten\n9.99\n14 stuks"
  },
  {
    "raw_text": "Witte Reus Toiletblok kracht actief oceaan\n\n60% kortingvandaag\n\n3.69\n1.48\n50 g\nKies\nLos\n5 Stuks"
  },
  {
    "raw_text": "Witte Reus Toiletblok paars actief provence\n\n60% kortingvandaag\n\n4.29\n1.72\n50 g"
  },
  {
    "raw_text": "AH Wasverzachter zeemineralen & cederhout\n1.99\n30 wasbeurten"
  },
  {
    "raw_text": "Antikal Fresh spray\n5.49\n0,8 l"
  },
  {
    "raw_text": "AH Glasdoekjes\n1.19\n30 stuks"
  },
  {
    "raw_text": "Dettol Allesreiniger original\n\n30% kortingvanaf maandag\n\n5.49\n3.84\n1,5 l"
  },
  {
    "raw_text": "Lenor Unstoppables geurbooster bloemenfris\n\n3 VOOR 14.99vandaag\n\n11.99\n235 g"
  },
  {
    "raw_text": "HG Vloeibare ontstopper\n4.99\n0,5 l"
  },
  {
    "raw_text": "Page Aloë vera vochtig toiletpapier\n3.49\n74 stuks"
  },
  {
    "raw_text": "Finish Integrale machinereiniger citroen\n6.49\n250 ml"
  },
  {
    "raw_text": "Robijn Specials fleur & fijn wasmiddel\n9.99\n18 wasbeurten"
  },
  {
    "raw_text": "Vanish Vlekverwijderaar poeder voor witte was\n\n50% kortingvandaag\n\n8.99\n4.49\n470 g"
  },
  {
    "raw_text": "Robijn Wasverzachter passiebloem & bergamot\n\n3 voor 9.00vanaf maandag\n\n6.79\n39 wasbeurten"
  },
  {
    "raw_text": "Dubro Snelontkalker\n3.29\n0,5 l"
  },
  {
    "raw_text": "AH Containerzakken 140 liter\n1.99\n3 stuks"
  },
  {
    "raw_text": "Ecover Afwasmiddel citroen & aloë vera\n\n2e gratisvanaf maandag\n\n3.59\n450 ml"
  },
  {
    "raw_text": "AH Vuilniszakken trekband 60 liter citrus\n2.49\n10 stuks"
  },
  {
    "raw_text": "Kleenex Ultra clean maxi keukenpapier\n5.89\n2 stuks"
  },
  {
    "raw_text": "Sorbo Smartbrush\n4.35\nper stuk"
  },
  {
    "raw_text": "Robijn 3-in-1 Wascapsules stralend wit\n9.99\n15 wasbeurten"
  },
  {
    "raw_text": "AH Power toiletblokken oceaan blauw water\n2.39\n2 stuks"
  },
  {
    "raw_text": "WC-Eend Toiletreiniger coastal forest\n\n2e gratisvanaf maandag\n\n3.75\n0,75 l"
  },
  {
    "raw_text": "Robijn Wasverzachter pink sensation\n\n3 voor 9.00vanaf maandag\n\n6.79\n39 wasbeurten"
  },
  {
    "raw_text": "AH Houten wasknijpers\n2.19\n48 stuks"
  },
  {
    "raw_text": "AH Containerzakken 140 liter\n1.59\n10 stuks"
  },
  {
    "raw_text": "AH Luchtverfrisser gel bloeiende lavendel\n0.89\n150 g"
  },
  {
    "raw_text": "The Good Roll The panda edition paper bag\n4.79\n4 rollen"
  },
  {
    "raw_text": "Sun Brilliant shine plus vaatwascapsules\n\n2e gratisvanaf maandag\n\n10.99\n16 stuks"
  },
  {
    "raw_text": "AH Badkamerreiniger spray\n2.19\n0,75 l"
  },
  {
    "raw_text": "Cif Cream Citroen + Gratis Schuurspons\n\nonline30% pakketkortingvandaag\n\n4.78\n3.35\nper pakket"
  },
  {
    "raw_text": "Ecover Wc-reiniger zeebries & salie\n\n2e gratisvanaf maandag\n\n3.89\n0,75 l"
  },
  {
    "raw_text": "HG Koffiemachine ontkalker citroenzuur\n5.79\n0,5 l"
  },
  {
    "raw_text": "Nalys Vochtvangers keukenpapier 4=8 rol\n\n1 + 1 GRATISvandaag\n\n11.09\n4 stuks"
  },
  {
    "raw_text": "Robijn Wasverzachter zwitsal geur\n9.19\n50 wasbeurten"
  },
  {
    "raw_text": "Lenor Vloeibaar wasmiddel zeebries\n\n3 VOOR 14.99vandaag\n\n13.99\n20 wasbeurten"
  },
  {
    "raw_text": "Robijn Color morgenfris wasmiddel\n17.49\n19 wasbeurten"
  },
  {
    "raw_text": "Page Puur toiletpapier\n3.49\n4 rollen\nKies\nLos\n6 Stuks"
  },
  {
    "raw_text": "Witte Reus Waspoeder color\n\n1 + 1 GRATISvandaag\n\n11.49\n23 wasbeurten"
  },
  {
    "raw_text": "AH Toiletblok dennen\n0.99\n40 g"
  },
  {
    "raw_text": "Vanish Vlekverwijderaar poeder gekleurde was\n\n50% kortingvandaag\n\n12.99\n6.49\n720 g"
  },
  {
    "raw_text": "Marcel's Green Soap Wasmiddel color peach jasmine navulling\n\n2e Halve Prijsvandaag\n\n9.79\n23 wasbeurten"
  },
  {
    "raw_text": "Lenor Vloeibaar wasmiddel gouden orchidee\n\n3 VOOR 14.99vandaag\n\n13.99\n20 wasbeurten"
  },
  {
    "raw_text": "Nalys Eindeloos toiletpapier 4=15 rol 2-pack\n\nonlinePakketkortingvandaag\n\n13.98\n6.99\n2 stuks"
  },
  {
    "raw_text": "Swiffer Duster navulling giga pack\n24.99\n23 stuks"
  },
  {
    "raw_text": "AH Zeepspons staalwol\n0.99\n10 stuks"
  },
  {
    "raw_text": "Marcel's Green Soap Allesreiniger lavendel & rozemarijn\n3.49\n0,75 l"
  },
  {
    "raw_text": "AH Afwasmiddel extra power\n1.49\n0,5 l"
  },
  {
    "raw_text": "Color Reus Wasmiddel vloeibaar gel kleur\n\n1 + 1 GRATISvandaag\n\n21.98\n77 wasbeurten"
  },
  {
    "raw_text": "Kleenex Take a moment zakdoekjes\n1.85\n6 stuks"
  },
  {
    "raw_text": "AH Kalkreiniger\n1.39\n0,5 l"
  },
  {
    "raw_text": "AH Viscosespons golf\n1.25\nper stuk"
  },
  {
    "raw_text": "Glade Luchtverfrisser spray sandalwood jasmine\n\n40% kortingvanaf maandag\n\n2.19\n1.31\n300 ml"
  },
  {
    "raw_text": "Marcel's Green Soap Allesreiniger sandelhout & kar\n3.49\n0,75 l"
  },
  {
    "raw_text": "Witte Reus Toiletblok kracht actief bloesem\n\n60% kortingvandaag\n\n6.99\n2.80\n100 g"
  },
  {
    "raw_text": "AH Luchtverfrisser gel frisse oceaanbries\n0.89\n150 g"
  },
  {
    "raw_text": "Sorbo Wonder sponge melaminespons\n2.75\n4 stuks"
  },
  {
    "raw_text": "Fleuril Renew white & light wasmiddel\n\n1 + 1 GRATISvandaag\n\n13.99\n29 wasbeurten"
  },
  {
    "raw_text": "Mr Muscle Badkamerreiniger spray\n3.59\n0,5 l"
  },
  {
    "raw_text": "HG Glasreiniger\n3.99\n0,5 l"
  },
  {
    "raw_text": "HG Voegenreiniger\n6.79\n0,5 l"
  },
  {
    "raw_text": "HG Haarontstopper\n10.69\n450 ml"
  },
  {
    "raw_text": "Ambi Pur 3volution fris linnen navulling\n\n40% kortingvanaf maandag\n\n6.29\n3.77\n20 ml"
  },
  {
    "raw_text": "Seepje Wasmiddel universeel\n\n2e Halve Prijsvandaag\n\n10.99\n23 wasbeurten"
  },
  {
    "raw_text": "Neutral Wasmiddel Voordeelpakket\n\nonlinePakketkortingvandaag\n\n17.38\n13.03\nper pakket"
  },
  {
    "raw_text": "Dettol Schoonmaakdoekjes oceaanfris\n\n30% kortingvanaf maandag\n\n4.49\n3.14\n72 stuks"
  },
  {
    "raw_text": "Dreft Platinum plus vaatwastabletten original\n\n2e gratisvanaf maandag\n\n24.99\n36 stuks\nKies\nLos\n4 Stuks"
  },
  {
    "raw_text": "Blue Wonder Allesreiniger\n3.99\n0,75 l"
  },
  {
    "raw_text": "Ambi Pur 3Volution Navulling Thai Orchid\n\n40% kortingvanaf maandag\n\n6.29\n3.77\n20 ml"
  },
  {
    "raw_text": "Zwarte Reus Wasmiddel vloeibaar gel zwart\n\n1 + 1 GRATISvandaag\n\n9.29\n19 wasbeurten"
  },
  {
    "raw_text": "Color Reus Waspoeder wasmiddel kleur\n\n1 + 1 GRATISvandaag\n\n21.98\n45 wasbeurten"
  },
  {
    "raw_text": "Vileda Microvezeldoeken\n4.99\n4 stuks"
  },
  {
    "raw_text": "AH Wascapsules 3-in-1 wit\n5.09\n24 wasbeurten"
  },
  {
    "raw_text": "Swiffer Vloerdoekjes vochtig navulling\n10.49\n20 stuks"
  },
  {
    "raw_text": "Ecover Vloeibaar wasmiddel wol & fijnwas\n\n2e Halve Prijsvandaag\n\n7.99\n22 wasbeurten"
  },
  {
    "raw_text": "Ariel Ultra+ vlekverwijderaar wasmiddel\n\n1 + 1 GRATISvandaag\n\n15.99\n20 wasbeurten"
  },
  {
    "raw_text": "Dettol Schoonmaakdoekjes cleanser\n\n30% kortingvanaf maandag\n\n2.49\n1.74\n30 stuks"
  },
  {
    "raw_text": "Dr. Beckmann Anti-kleurdoorloop doekjes\n3.79\n24 wasbeurten"
  },
  {
    "raw_text": "Page Compleet schoon toiletpapier maxi\n3.19\n4 stuks"
  },
  {
    "raw_text": "HG Groene aanslagreiniger\n9.29\n1 l"
  },
  {
    "raw_text": "Ariel Original family pack XL wasmiddel\n\n2e gratisvanaf maandag\n\n29.29\n44 wasbeurten"
  },
  {
    "raw_text": "Ecover Allesreiniger magnolia & bamboo\n\n2e gratisvanaf maandag\n\n3.49\n1 l"
  },
  {
    "raw_text": "Kleenex Allergy comfort zakdoekjes\n2.29\n8 stuks"
  },
  {
    "raw_text": "AH Stofzuigerzakken type Philips/Electrolux\n4.99\n4 stuks"
  },
  {
    "raw_text": "AH Containerzakken 240 liter\n2.99\n3 stuks"
  },
  {
    "raw_text": "Nalys Xtra multi-gebruik papier\n\nonline35% Op=Op kortingvanaf maandag\n\n10.47\n6.81\n6 rollen"
  },
  {
    "raw_text": "Lenor Vloeibaar wasmiddel cotton\n\n3 VOOR 14.99vandaag\n\n13.99\n20 wasbeurten"
  },
  {
    "raw_text": "Glade Touch & fresh relaxing zen 2 navullingen\n\n40% kortingvanaf maandag\n\n3.79\n2.27\n2 x 10 ml"
  },
  {
    "raw_text": "Marcel's Green Soap Wasverzachter vanilla & cotton\n\n2e Halve Prijsvandaag\n\n4.49\n30 wasbeurten"
  },
  {
    "raw_text": "Biotex Handwas vloeibaar\n6.69\n1 l"
  },
  {
    "raw_text": "AH Schuurspons hard\n0.99\n3 stuks"
  },
  {
    "raw_text": "AH Statische stofdoekjes + houder\n1.29\nper set"
  },
  {
    "raw_text": "Dreft Afwasmiddel max power original\n\n2e gratisvanaf maandag\n\n7.59\n0,73 l"
  },
  {
    "raw_text": "HG Oven, grill en barbecuereiniger\n9.39\n0,5 l"
  },
  {
    "raw_text": "Finish Protector\n7.69\nper stuk"
  },
  {
    "raw_text": "Ambi Pur Toiletblok bloesem\n2.99\n55 ml"
  },
  {
    "raw_text": "Swiffer Duster starterkit\n4.99\nper stuk"
  },
  {
    "raw_text": "Seepje Afwasmiddel sinaasappel geur\n\n2e gratisvanaf maandag\n\n3.29\n0,5 l"
  },
  {
    "raw_text": "Finish Quantum vaatwastabletten\n15.49\n32 stuks"
  },
  {
    "raw_text": "Ecover Vloeibaar wasmiddel universal\n\n2e Halve Prijsvandaag\n\n14.39\n28 wasbeurten"
  },
  {
    "raw_text": "Robijn Wasverzachter jasmijn & sandelhout\n\n3 voor 9.00vanaf maandag\n\n6.79\n39 wasbeurten"
  },
  {
    "raw_text": "Blue Wonder Vloerreiniger\n4.09\n0,75 l"
  },
  {
    "raw_text": "AH Werkborstel\n2.99\nper stuk"
  },
  {
    "raw_text": "Ariel Vloeibaar+ color care wasmiddel\n\n1 + 1 GRATISvandaag\n\n23.99\n30 wasbeurten"
  },
  {
    "raw_text": "Vanish Vlekverwijderaar poeder voor witte was\n\n50% kortingvandaag\n\n12.99\n6.49\n720 g"
  },
  {
    "raw_text": "AH Diepvrieszakken met sluitstrip 3 liter\n2.99\n75 stuks"
  },
  {
    "raw_text": "Robijn Wasverzachter paradise secret\n\n3 voor 9.00vanaf maandag\n\n7.29\n38 wasbeurten"
  },
  {
    "raw_text": "Glade Langdurig muguet gel\n\n40% kortingvanaf maandag\n\n1.65\n0.99\nper stuk"
  },
  {
    "raw_text": "Ambi Pur Toiletblok lavendel\n2.99\n55 ml"
  },
  {
    "raw_text": "Toppits Zipper multi-functionele zakken 3liter\n3.49\n8 stuks"
  },
  {
    "raw_text": "Witte Reus Toiletblok deluxe delicate magnolia\n\n60% kortingvandaag\n\n7.99\n3.20\n100 g"
  },
  {
    "raw_text": "Neutral Wit parfumvrij wasmiddel\n\n2e Halve Prijsvandaag\n\n8.69\n20 wasbeurten"
  },
  {
    "raw_text": "Swiffer Vloerdoekjes droog navulling maxi pack\n9.49\n30 stuks"
  },
  {
    "raw_text": "Ambi Pur Luchtverfrisser badkamer & toilet katoen\n\n40% kortingvanaf maandag\n\n4.79\n2.87\nper stuk"
  },
  {
    "raw_text": "Lenor Fresh air wasverzachter fleurige bloesem\n\n3 VOOR 14.99vandaag\n\n8.19\n36 wasbeurten"
  },
  {
    "raw_text": "Ambi Pur Ap pink hibiscus rose\n3.49\n0,75 l"
  },
  {
    "raw_text": "Dettol Schoonmaakdoekjes appelbloesem\n\n30% kortingvanaf maandag\n\n3.79\n2.65\n48 stuks"
  },
  {
    "raw_text": "Sun Brilliant shine plus vaatwascapsules\n\n2e gratisvanaf maandag\n\n23.19\n34 stuks"
  },
  {
    "raw_text": "AH Vaatdoek badstof\n1.69\n2 stuks"
  },
  {
    "raw_text": "AH Schoonmaakdoekje non-woven\n2.39\nper rol"
  },
  {
    "raw_text": "Robijn Color bohemian blossom wasmiddel\n18.39\n19 wasbeurten"
  },
  {
    "raw_text": "Kleenex Flexi clean maxi keukenpapier\n5.99\n2 stuks"
  },
  {
    "raw_text": "Ariel Vloeibaar color wasmiddel\n\n2e gratisvanaf maandag\n\n19.99\n30 wasbeurten"
  },
  {
    "raw_text": "Robijn Wasverzachter tropical\n\n3 voor 9.00vanaf maandag\n\n7.29\n38 wasbeurten"
  },
  {
    "raw_text": "AH Stofzuigerzakken type Bosch/Siemens\n4.99\n4 stuks"
  },
  {
    "raw_text": "Neutral Wasmiddel zwart en donker parfumvrij\n\n2e Halve Prijsvandaag\n\n8.69\n20 wasbeurten"
  },
  {
    "raw_text": "Glade Touch & fresh sandalwood navulling\n\n40% kortingvanaf maandag\n\n3.79\n2.27\n20 ml"
  },
  {
    "raw_text": "Persil Deep clean wasmiddel vloeibaar sensitive\n\n1 + 1 GRATISvandaag\n\n10.99\n18 wasbeurten"
  },
  {
    "raw_text": "Robijn 3-in-1 Wascapsules black velvet\n12.49\n15 wasbeurten"
  },
  {
    "raw_text": "Robijn Dry wash spray pink sensation\n10.89\n200 ml"
  },
  {
    "raw_text": "Seepje Wasmiddel wol en fijn vrolijke lotus\n\n2e Halve Prijsvandaag\n\n7.99\n23 wasbeurten"
  },
  {
    "raw_text": "Robijn Collections capsules spa sensation\n14.15\n15 wasbeurten"
  },
  {
    "raw_text": "Lenor Wasverzachter robijn jasmijn\n\n3 VOOR 14.99vandaag\n\n9.99\n55 wasbeurten"
  },
  {
    "raw_text": "HG Onderhoudsmonteur voor (vaat)wasmachines\n11.99\n200 g"
  },
  {
    "raw_text": "AH Oxi power vlekverwijdering poeder kleur\n3.19\n750 g"
  },
  {
    "raw_text": "Swirl Embossed trekband\n2.99\n12 stuks"
  },
  {
    "raw_text": "Swiffer Vloerreiniger navulling xxl\n7.79\n12 stuks"
  },
  {
    "raw_text": "HG Toiletgel extra sterk\n7.39\n0,5 l"
  },
  {
    "raw_text": "Dr. Beckmann Super wit\n3.79\n4 wasbeurten"
  },
  {
    "raw_text": "Ecover Allesreiniger\n\n2e gratisvanaf maandag\n\n4.69\n0,5 l"
  },
  {
    "raw_text": "Witte Reus Brilliant gel alpine lake\n\n60% kortingvandaag\n\n4.29\n1.72\n42 g"
  },
  {
    "raw_text": "Lenor Zeebries wasmiddelcapsules\n\n3 VOOR 14.99vandaag\n\n11.99\n15 wasbeurten"
  },
  {
    "raw_text": "Seepje Wasmiddel navulzak universeel\n\n2e Halve Prijsvandaag\n\n9.99\n23 wasbeurten"
  },
  {
    "raw_text": "Calgon Wasmachinereiniger en anti kalk gel\n7.99\n0,75 l"
  },
  {
    "raw_text": "Lenor Pods gouden orchidee wasmiddelcapsules\n\n3 VOOR 14.99vandaag\n\n11.99\n15 wasbeurten"
  },
  {
    "raw_text": "Dreft Platinum plus original vaatwastabletten\n\n2e gratisvanaf maandag\n\n39.99\n59 stuks"
  },
  {
    "raw_text": "Ecover Wc-reiniger lemon & orange\n\n2e gratisvanaf maandag\n\n4.75\n0,75 l"
  },
  {
    "raw_text": "Vanish Vlekverwijderaar poeder gekleurde was\n\n50% kortingvandaag\n\n8.99\n4.49\n470 g"
  },
  {
    "raw_text": "Lenor Fresh air wasverzachter stralende zon\n\n3 VOOR 14.99vandaag\n\n8.19\n36 wasbeurten"
  },
  {
    "raw_text": "AH Stofzuigerzakken type Miele G/N\n4.99\n4 stuks"
  },
  {
    "raw_text": "HG Natuursteen aanrechtbladreiniger\n6.79\n0,5 l"
  },
  {
    "raw_text": "Ambi Pur Luchtverfrisser spray vleugje bloesem\n\n40% kortingvanaf maandag\n\n4.49\n2.69\n185 ml"
  },
  {
    "raw_text": "Robijn Color kokos wasmiddel\n18.39\n19 wasbeurten"
  },
  {
    "raw_text": "Finish Ultimate vaatwastabletten\n10.39\n17 stuks"
  },
  {
    "raw_text": "Witte Reus Waspoeder wit\n\n1 + 1 GRATISvandaag\n\n11.49\n23 wasbeurten"
  },
  {
    "raw_text": "Neutral Parfumvrij waspoeder witte was\n\n2e Halve Prijsvandaag\n\n7.99\n18 wasbeurten"
  },
  {
    "raw_text": "Vileda Handschoenen sensitive easy fit M\n2.99\nper stuk"
  },
  {
    "raw_text": "Marcel's Green Soap Wasmiddel patchouli cranberry navulling\n\n2e Halve Prijsvandaag\n\n9.79\n23 wasbeurten"
  },
  {
    "raw_text": "Ariel Poeder color\n\n2e gratisvanaf maandag\n\n16.99\n25 wasbeurten"
  },
  {
    "raw_text": "HG Keukenontstopper\n9.29\n1 l"
  },
  {
    "raw_text": "Vileda Schuursponsen glitzi power 2-pack\n3.49\n2 stuks"
  },
  {
    "raw_text": "Air Wick Freshmatic luchtverfrisser navulling\n\n40% kortingvanaf maandag\n\n6.15\n3.69\n250 ml"
  },
  {
    "raw_text": "Marcel's Green Soap Afwasmiddel basilicum & vertivert gras\n3.29\n0,5 l"
  },
  {
    "raw_text": "Dettol Schoonmaakdoekjes eucalyptus en limoen\n\n30% kortingvanaf maandag\n\n3.79\n2.65\n48 stuks"
  },
  {
    "raw_text": "Robijn Collection tropical 3in1 capsules\n13.55\n15 wasbeurten"
  },
  {
    "raw_text": "Vileda Handschoenen Comfort & Care M\n2.99\nper stuk"
  },
  {
    "raw_text": "Dubro Afwasmiddel limoen fris\n2.99\n0,55 l"
  },
  {
    "raw_text": "Air Wick Luchtverfrisser spray pure katoen\n\n40% kortingvanaf maandag\n\n4.45\n2.67\n250 ml"
  },
  {
    "raw_text": "Witte Reus Toiletblok kracht actief lavendel\n\n60% kortingvandaag\n\n6.99\n2.80\n100 g"
  },
  {
    "raw_text": "Glorix Power5 ocean duo pack wc-blok 2-pack\n\n2e gratisvanaf maandag\n\n7.79\n2 stuks"
  },
  {
    "raw_text": "Finish Ultimate plus vaatwastabletten citroen\n15.49\n22 stuks"
  },
  {
    "raw_text": "HG Kalkweg schuimspray\n5.39\n0,5 l"
  },
  {
    "raw_text": "HG Duo ontstopper\n14.29\n1 l"
  },
  {
    "raw_text": "Klok Waspoeder kleur parfumvrij\n\n2e Halve Prijsvandaag\n\n8.49\n18 wasbeurten"
  },
  {
    "raw_text": "Blue Wonder Allesreiniger spray\n4.55\n0,75 l"
  },
  {
    "raw_text": "AH Toiletblok frisse oceaanbries navulling\n2.19\n4 stuks"
  },
  {
    "raw_text": "Ariel Vloeibaar original wasmiddel\n\n2e gratisvanaf maandag\n\n19.99\n30 wasbeurten"
  },
  {
    "raw_text": "SEL Wasbenzine\n2.99\n1 l"
  },
  {
    "raw_text": "Ambi Pur 3Volution Navulling Vleugje Bloesem\n\n40% kortingvanaf maandag\n\n6.19\n3.71\n20 ml"
  },
  {
    "raw_text": "Dr. Beckmann Ossengalzeep\n2.85\n100 g"
  },
  {
    "raw_text": "Destop Haarontstopper sodagel\n6.79\n1 l"
  },
  {
    "raw_text": "Method Keukenreiniger spray\n\n2e gratisvanaf maandag\n\n6.49\n0,83 l"
  },
  {
    "raw_text": "Neutral Wol & fijn vloeibaar wasmiddel\n\n2e Halve Prijsvandaag\n\n8.69\n20 wasbeurten"
  },
  {
    "raw_text": "Ambi Pur 3Volution Navulling Ochtend Dauw\n\n40% kortingvanaf maandag\n\n6.29\n3.77\n20 ml"
  },
  {
    "raw_text": "Robijn Stralend wit 3-in-1 wascapsules\n17.29\n26 wasbeurten"
  },
  {
    "raw_text": "Seepje Afwasmiddel spetterende eucalyptus\n\n2e gratisvanaf maandag\n\n3.29\n0,5 l"
  },
  {
    "raw_text": "Glade Pure clean linen spray\n\n40% kortingvanaf maandag\n\n2.39\n1.43\n300 ml"
  },
  {
    "raw_text": "Marcel's Green Soap Wasverzachter peach jasmine\n\n2e Halve Prijsvandaag\n\n4.49\n30 wasbeurten"
  },
  {
    "raw_text": "Ariel 3-in-1 pods original wasmiddelcapsules\n\n1 + 1 GRATISvandaag\n\n49.49\n65 wasbeurten"
  },
  {
    "raw_text": "Ajax Shower power spray navulling\n2.99\n0,75 l"
  },
  {
    "raw_text": "Air Wick Luchtverfrisser spray pure lentedauw\n\n40% kortingvanaf maandag\n\n4.45\n2.67\n250 ml"
  },
  {
    "raw_text": "Glade Luchtverfrisser spray vanilla blossom\n\n40% kortingvanaf maandag\n\n2.39\n1.43\n300 ml"
  },
  {
    "raw_text": "Seepje Wasverzachter sandelhout en perzik\n\n2e Halve Prijsvandaag\n\n4.49\n30 wasbeurten"
  },
  {
    "raw_text": "Seepje Wasmiddel kleur\n\n2e Halve Prijsvandaag\n\n10.99\n23 wasbeurten"
  },
  {
    "raw_text": "Marcel's Green Soap Vaatwas capsules all-in-one\n11.99\n25 stuks"
  },
  {
    "raw_text": "Ajax Eucalyptus spray\n3.49\n0,75 l"
  },
  {
    "raw_text": "Dr. Beckmann Geurverwijderaar\n5.49\n0,5 l"
  },
  {
    "raw_text": "AH Sponsdoekjes\n1.45\n5 stuks"
  },
  {
    "raw_text": "HG Eco tegen stinkend wasgoed\n7.89\n500 g"
  },
  {
    "raw_text": "Witte Reus Color 3+1 power wasmiddel capsules kleur\n\n1 + 1 GRATISvandaag\n\n8.49\n14 wasbeurten"
  },
  {
    "raw_text": "Witte Reus Wasmiddel vloeibaar gel wit\n\n1 + 1 GRATISvandaag\n\n21.98\n77 wasbeurten"
  },
  {
    "raw_text": "Marcel's Green Soap Wasmiddel univereel vanille cotton\n\n2e Halve Prijsvandaag\n\n10.79\n23 wasbeurten"
  },
  {
    "raw_text": "Method Allesreiniger spray roze pompelmoes\n\n2e gratisvanaf maandag\n\n6.49\n0,83 l"
  },
  {
    "raw_text": "Marcel's Green Soap Allesreiniger sandelhout navulling\n2.99\n0,5 l"
  },
  {
    "raw_text": "Robijn Wasverzachter spa sensation\n\n3 voor 9.00vanaf maandag\n\n7.29\n38 wasbeurten"
  },
  {
    "raw_text": "Ambi Pur Luchtverfrisser spray ochtend dauw\n\n40% kortingvanaf maandag\n\n4.49\n2.69\n185 ml"
  },
  {
    "raw_text": "AH Fleece Stofdoek\n0.99\nper stuk"
  },
  {
    "raw_text": "AH Hersluitbare zakjes 4,5 en 6 liter\n3.29\n30 stuks"
  },
  {
    "raw_text": "Seepje Wasverzachter pioenroos en cederhout\n\n2e Halve Prijsvandaag\n\n4.49\n30 wasbeurten"
  },
  {
    "raw_text": "AH Luchtverfrisser jasmijn & citrus\n1.99\n150 ml"
  },
  {
    "raw_text": "Ecover Badkamer reiniger\n\n2e gratisvanaf maandag\n\n4.99\n0,5 l"
  },
  {
    "raw_text": "Page Compleet schoon toiletpapier\n4.29\n6 stuks"
  },
  {
    "raw_text": "Dreft Platinum plus vaatwastabletten 6-pack\n\n2e gratisvanaf maandag\n\n48.79\n72 stuks"
  },
  {
    "raw_text": "Glade Touch & fresh pure clean linen navulling\n\n40% kortingvanaf maandag\n\n3.79\n2.27\n20 ml"
  },
  {
    "raw_text": "Lenor Fresh air wasverzachter noorderlicht\n\n3 VOOR 14.99vandaag\n\n8.19\n36 wasbeurten"
  },
  {
    "raw_text": "Witte Reus Toiletblok deluxe midnight bouquet\n\n60% kortingvandaag\n\n4.29\n1.72\nper stuk"
  },
  {
    "raw_text": "Lenor Wasverzacher gouden orchidee\n\n3 VOOR 14.99vandaag\n\n9.99\n55 wasbeurten"
  },
  {
    "raw_text": "Swiffer Vloerdoekjes droog navulling\n4.69\n13 stuks"
  },
  {
    "raw_text": "Dreft Platinum plus vaatwastabletten citroen\n\n2e gratisvanaf maandag\n\n39.99\n59 stuks"
  },
  {
    "raw_text": "SEL Terpentine\n2.99\n1 l"
  },
  {
    "raw_text": "AH Viscosedoekjes\n0.79\n3 stuks"
  },
  {
    "raw_text": "Ambi Pur Lavender & rosemary navulling\n5.89\n165 ml"
  },
  {
    "raw_text": "Dr. Beckmann Pre Wash sweat & deo\n3.79\n250 ml"
  },
  {
    "raw_text": "Dr. Beckmann Wasmachine onderhoudsreiniger\n3.99\n250 ml"
  },
  {
    "raw_text": "Witte Reus Toiletblok kracht actief exotisch\n\n60% kortingvandaag\n\n3.69\n1.48\n50 g"
  },
  {
    "raw_text": "Ambi Pur Luchtverfrisser badkamer & toilet\n\n40% kortingvanaf maandag\n\n4.79\n2.87\nper stuk"
  },
  {
    "raw_text": "HG Nespresso ontkalker\n9.29\n0,5 l"
  },
  {
    "raw_text": "Witte Reus Toiletblok blauw actief eucalyptus 2pack\n\n60% kortingvandaag\n\n7.99\n3.20\n100 g"
  },
  {
    "raw_text": "AH Toiletblok lavendel navulling\n2.19\n4 stuks"
  },
  {
    "raw_text": "Glorix Power5 citrus duo pack wc-blok 2-pack\n\n2e gratisvanaf maandag\n\n7.59\n2 stuks"
  },
  {
    "raw_text": "Marcel's Green Soap Allesreiniger lavendel navulling\n2.99\n0,5 l"
  },
  {
    "raw_text": "Glade Pure clean linen\n\n40% kortingvanaf maandag\n\n1.65\n0.99\n150 g"
  },
  {
    "raw_text": "Pledge Classic\n3.49\n250 ml"
  },
  {
    "raw_text": "Dr. Beckmann Pre wash vloeibaar met borstel\n3.79\n250 ml"
  },
  {
    "raw_text": "Vim Schuurpoeder citroen fris\n1.39\n500 g"
  },
  {
    "raw_text": "Dettol Allesreiniger spray mandarijn & citroen\n\n30% kortingvanaf maandag\n\n3.99\n2.79\n0,5 l"
  },
  {
    "raw_text": "HG Afvoerreiniger\n4.69\n6 stuks"
  },
  {
    "raw_text": "Sorbo Microvezeldoek zwart grijs\n4.99\n5 stuks"
  },
  {
    "raw_text": "Seepje Afwasmiddel tintelfrisse limoen refill\n\n2e gratisvanaf maandag\n\n3.29\n0,5 l"
  },
  {
    "raw_text": "AH Stofzuigerzakken type Miele F/J/M/H\n4.99\n4 stuks"
  },
  {
    "raw_text": "HG Vlekverwijderaar extreem sterk\n9.49\n0,5 l"
  },
  {
    "raw_text": "HG Stickerverwijderaar\n7.89\n300 ml"
  },
  {
    "raw_text": "Dr. Beckmann Active white doekjes\n3.79\n15 wasbeurten"
  },
  {
    "raw_text": "HG Zweet vlekkenverwijderaar\n6.89\n250 ml"
  },
  {
    "raw_text": "HG Koffiemachine reinigingstabletten\n7.99\n10 stuks"
  },
  {
    "raw_text": "HG Eco koffiemachine ontkalker citroenzuur\n5.89\n0,5 l"
  },
  {
    "raw_text": "AH Power toiletblok turquoise\n2.39\n2 stuks"
  },
  {
    "raw_text": "AH Geurtwist toiletblok rozen & zomerfruit\n2.49\nper stuk"
  },
  {
    "raw_text": "Antikal toiletgel\n3.49\n0,75 l"
  },
  {
    "raw_text": "Sorbo Badkamerspons krasvrij\n3.49\nper stuk"
  },
  {
    "raw_text": "Method Allesreiniger spray lavendel\n\n2e gratisvanaf maandag\n\n6.49\n0,83 l"
  },
  {
    "raw_text": "Lenor Wasverzachter zeebries\n\n3 VOOR 14.99vandaag\n\n9.99\n55 wasbeurten"
  },
  {
    "raw_text": "Glade Luchtverfrisser spray lavender\n\n40% kortingvanaf maandag\n\n2.19\n1.31\n300 ml"
  },
  {
    "raw_text": "Glade Touch & fresh lavender 2 navullingen\n\n40% kortingvanaf maandag\n\n3.79\n2.27\n20 ml"
  },
  {
    "raw_text": "Witte Reus Toiletblok blauw actief bloesem 2-pack\n\n60% kortingvandaag\n\n7.99\n3.20\n100 g"
  },
  {
    "raw_text": "AH Geurtwist toiletblok jasmijn & citrus\n2.49\nper stuk"
  },
  {
    "raw_text": "AH Spray geureditie jasmijn & citrus navul\n1.49\n24 ml"
  },
  {
    "raw_text": "Lenor Vloeibaar wasmiddel amethist\n\n3 VOOR 14.99vandaag\n\n13.99\n20 wasbeurten"
  },
  {
    "raw_text": "Everdrop Toiletreiniger navulling\n3.19\nper stuk"
  },
  {
    "raw_text": "Ariel Poeder original\n\n2e gratisvanaf maandag\n\n16.99\n25 wasbeurten"
  },
  {
    "raw_text": "Lenor Wasverzachter jasmijn bloem\n\n3 VOOR 14.99vandaag\n\n9.99\n55 wasbeurten"
  },
  {
    "raw_text": "HG Kookplaatreiniger extra sterk\n6.79\n250 ml"
  },
  {
    "raw_text": "Glade Touch & fresh houder pure clean linen\n\n40% kortingvanaf maandag\n\n3.39\n2.03\n10 ml"
  },
  {
    "raw_text": "Swirl Vuilniszakken met handvatten 10L\n2.49\n37 stuks"
  },
  {
    "raw_text": "Witte Reus White 3+1 power wasmiddel capsules wit\n\n1 + 1 GRATISvandaag\n\n8.49\n14 wasbeurten"
  },
  {
    "raw_text": "Marcel's Green Soap Wasverzachter patchouli & cranberry\n\n2e Halve Prijsvandaag\n\n4.49\n30 wasbeurten"
  },
  {
    "raw_text": "Swirl Pedaalemmerzak vanille lavendel 35l\n2.99\n9 stuks"
  },
  {
    "raw_text": "Ariel Vloeibaar+ active wasmiddel\n\n1 + 1 GRATISvandaag\n\n23.99\n30 wasbeurten"
  },
  {
    "raw_text": "Robijn Wasverzachter zwitsal\n\n3 voor 9.00vanaf maandag\n\n7.29\n38 wasbeurten"
  },
  {
    "raw_text": "Robijn Wasverzachter beautiful mystery\n\n3 voor 9.00vanaf maandag\n\n7.29\n38 wasbeurten"
  },
  {
    "raw_text": "AH Dweil gestikt\n1.19\nper stuk"
  },
  {
    "raw_text": "Ariel Vloeibaar+ touch of lenor wasmiddel\n\n1 + 1 GRATISvandaag\n\n23.99\n30 wasbeurten"
  },
  {
    "raw_text": "Sorbo Wegwerphandschoen nitril\n5.99\n20 stuks"
  },
  {
    "raw_text": "Ecover Vloeibaar wasmiddel zwart\n\n2e Halve Prijsvandaag\n\n7.49\n22 wasbeurten"
  },
  {
    "raw_text": "Blue Wonder Desinfectie bad & wc spray\n5.09\n0,75 l"
  },
  {
    "raw_text": "HG Waterdicht synthetisch textiel\n11.59\n300 ml"
  },
  {
    "raw_text": "Lenor Fresh air wasverzachter tropical sunset\n\n3 VOOR 14.99vandaag\n\n8.19\n36 wasbeurten"
  },
  {
    "raw_text": "HG Laminaatreiniger\n9.29\n1 l"
  },
  {
    "raw_text": "Robijn Wascapsules black velvet\n21.45\n26 wasbeurten"
  },
  {
    "raw_text": "Swirl Pedaalemmerzak vanille lavendel 20 liter\n3.29\n12 stuks"
  },
  {
    "raw_text": "Vapona Mierenlokdoos\n5.99\n2 stuks"
  },
  {
    "raw_text": "AH Luchtverfrisser zeemineralen & cedarhout\n1.99\n150 ml"
  },
  {
    "raw_text": "Witte Reus Toiletblok blauw actief hygiene\n\n60% kortingvandaag\n\n10.99\n4.40\n150 g"
  },
  {
    "raw_text": "Robijn Dry wash spray zwitsal\n10.89\n200 ml"
  },
  {
    "raw_text": "Seepje Wasmiddel navulzak kleur\n\n2e Halve Prijsvandaag\n\n9.99\n23 wasbeurten"
  },
  {
    "raw_text": "The Green Lab Co. Allesreiniger starter set\n5.95\nper stuk"
  },
  {
    "raw_text": "Ecover Vloeibaar wasmiddel kleur\n\n2e Halve Prijsvandaag\n\n14.39\n28 wasbeurten"
  },
  {
    "raw_text": "Swiffer Duster xxl starterkit\n9.59\nper stuk"
  },
  {
    "raw_text": "Pledge Houtolie spray\n3.49\n250 ml"
  },
  {
    "raw_text": "Toppits Magnetronfolie 2-in-1\n3.89\n15 meter"
  },
  {
    "raw_text": "Calgon Wasmachinereiniger anti kalk tabletten\n9.49\n17 wasbeurten"
  },
  {
    "raw_text": "Toppits Diepvrieszakken\n2.89\n40 stuks"
  },
  {
    "raw_text": "HG Nespresso reinigingscups\n10.69\n6 stuks"
  },
  {
    "raw_text": "Ecover Wasverzachter gardennia\n\n2e Halve Prijsvandaag\n\n4.89\n33 wasbeurten"
  },
  {
    "raw_text": "HG Eco kookplaatreiniger\n5.99\n0,5 l"
  },
  {
    "raw_text": "Sorbo Window dry wonderzeem\n3.49\nper stuk"
  },
  {
    "raw_text": "Sorbo Cooking care kookplaat- & ovenspons\n3.99\n2 stuks"
  },
  {
    "raw_text": "Persil Deep clean wasmiddel vloeibaar kleur\n\n1 + 1 GRATISvandaag\n\n10.99\n19 wasbeurten"
  },
  {
    "raw_text": "Witte Reus Waspoeder wasmiddel wit\n\n1 + 1 GRATISvandaag\n\n21.98\n45 wasbeurten"
  },
  {
    "raw_text": "Blue Wonder Desinfectie reiniger keuken\n4.79\n0,75 l"
  },
  {
    "raw_text": "Robijn Color zwitsal wasmiddel voordeelfles\n30.99\n34 wasbeurten"
  },
  {
    "raw_text": "HG Eco ontstopper\n8.99\n1 l"
  },
  {
    "raw_text": "Method Badkamerreiniger spray\n\n2e gratisvanaf maandag\n\n6.49\n0,83 l"
  },
  {
    "raw_text": "The Green Lab Co. Allesreiniger tablet bergamot\n4.95\n3 stuks"
  },
  {
    "raw_text": "Antikal Badkamerspray douche express\n5.49\n0,8 l"
  },
  {
    "raw_text": "Robijn Wasverzachter bohemian blossom\n\n3 voor 9.00vanaf maandag\n\n7.29\n38 wasbeurten"
  },
  {
    "raw_text": "HG Kachelruitjesreiniger\n9.99\n0,5 l"
  },
  {
    "raw_text": "HG Beeldschermreiniger\n5.39\n125 ml"
  },
  {
    "raw_text": "Blue Wonder Kalkreiniger\n4.55\n0,75 l"
  },
  {
    "raw_text": "Vanish Vlekverwijderaar gel gekleurde was\n\n50% kortingvandaag\n\n8.99\n4.49\n0,75 l"
  },
  {
    "raw_text": "HG Gelontstopper\n8.39\n1 l"
  },
  {
    "raw_text": "Witte Reus Toiletblok turquoise actief pacific\n\n60% kortingvandaag\n\n7.99\n3.20\n100 g"
  },
  {
    "raw_text": "Lenor Katoen wasmiddelcapsules\n\n3 VOOR 14.99vandaag\n\n11.99\n15 wasbeurten"
  },
  {
    "raw_text": "HG Alle nare geurtjes weg\n7.89\n0,5 l"
  },
  {
    "raw_text": "Vileda Schuursponsen colors\n2.99\n4 stuks"
  },
  {
    "raw_text": "Air Wick Freshmatic luchtverfrisser navulling\n\n40% kortingvanaf maandag\n\n6.29\n3.77\n250 ml"
  },
  {
    "raw_text": "Ambi Pur Badkamer en toilet luchtverfrisser\n\n40% kortingvanaf maandag\n\n5.29\n3.17\n7.5 ml"
  },
  {
    "raw_text": "Marcel's Green Soap Wasmiddel color peach jasmine\n\n2e Halve Prijsvandaag\n\n10.79\n23 wasbeurten"
  },
  {
    "raw_text": "Marcel's Green Soap Handafwas basicilum & vetiver refill\n2.99\n0,5 l"
  },
  {
    "raw_text": "Page Vochtig Probeerpakket\n\nonline20% pakketkorting\n\n10.65\n8.52\nper pakket"
  },
  {
    "raw_text": "Dreft 3 in 1 power lemon navulling\n\n2e gratisvanaf maandag\n\n6.99\n0,5 l"
  },
  {
    "raw_text": "HG Vetweg\n5.79\n0,5 l"
  },
  {
    "raw_text": "AH Microvezelhoes voor vloerwisser\n1.99\nper stuk"
  },
  {
    "raw_text": "Toppits Snackpapier\n3.99\n8 stuks"
  },
  {
    "raw_text": "HG Vlekken voorbehandeling extra sterk\n7.89\n0,5 l"
  },
  {
    "raw_text": "Tempo Fresh to go classic\n1.69\n10 stuks"
  },
  {
    "raw_text": "Glade Automatic spray clean linen navulling\n\n40% kortingvanaf maandag\n\n6.19\n3.71\n269 ml"
  },
  {
    "raw_text": "Ecover Wasverzachter appelbloesem & amandel\n\n2e Halve Prijsvandaag\n\n4.89\n33 wasbeurten"
  },
  {
    "raw_text": "Fleuril Renew color caps\n\n1 + 1 GRATISvandaag\n\n8.99\n15 wasbeurten"
  },
  {
    "raw_text": "Ambi Pur Ap mint jasmine\n3.49\n0,75 l"
  },
  {
    "raw_text": "Lenor Fresh air wasverzachter moonlight\n\n3 VOOR 14.99vandaag\n\n8.19\n36 wasbeurten"
  },
  {
    "raw_text": "AH Vlekkenspons wit\n1.49\n5 stuks"
  },
  {
    "raw_text": "Robijn Wasmiddel Kleur 2-pack\n\nonline30% volume voordeel\n\n32.38\n22.67\n2 stuks"
  },
  {
    "raw_text": "AH Gaatjeszeem absorberend 30x40cm\n1.99\nper stuk"
  },
  {
    "raw_text": "Klok Waspoeder wit parfumvrij\n\n2e Halve Prijsvandaag\n\n8.49\n18 wasbeurten"
  },
  {
    "raw_text": "Silvo Zilverpoets poetsmiddel voor zilver\n5.99\n175 ml"
  },
  {
    "raw_text": "HG Afvoerstankverwijderaar\n6.59\n500 g"
  },
  {
    "raw_text": "Glade Automatic spray vanilla blossom navul\n\n40% kortingvanaf maandag\n\n6.19\n3.71\n269 ml"
  },
  {
    "raw_text": "Vanish Vlekverwijderaar gel voor witte was\n\n50% kortingvandaag\n\n8.89\n4.44\n0,75 l"
  },
  {
    "raw_text": "Witte Reus Toiletblok blauw actief hygiene\n\n60% kortingvandaag\n\n7.59\n3.04\n100 g"
  },
  {
    "raw_text": "Super Ninja Tegen mieren\n5.99\n2 stuks"
  },
  {
    "raw_text": "Air Wick Essential mist vanille & framboos navul\n\n40% kortingvanaf maandag\n\n5.99\n3.59\n20 ml"
  },
  {
    "raw_text": "Marcel's Green Soap Wasmiddel patchouli cranberry\n\n2e Halve Prijsvandaag\n\n10.79\n23 wasbeurten"
  },
  {
    "raw_text": "HG Glasreiniger concentraat\n6.49\n0,5 l"
  },
  {
    "raw_text": "Air Wick Luchtverfrisser aziatische kersenbloesem\n\n40% kortingvanaf maandag\n\n4.79\n2.87\n250 ml"
  },
  {
    "raw_text": "Destop Gel express ontstopper met soda\n6.99\n0,95 l"
  },
  {
    "raw_text": "Ecover Waspoeder universal\n\n2e Halve Prijsvandaag\n\n10.49\n16 wasbeurten"
  },
  {
    "raw_text": "Ecover Afwasmiddel citroen & aloë vera\n\n2e gratisvanaf maandag\n\n5.69\n0,95 l"
  },
  {
    "raw_text": "HG Fruitvliegjesval\n7.89\nper stuk"
  },
  {
    "raw_text": "Air Wick Elektrische luchtverfrisser navulling\n\n40% kortingvanaf maandag\n\n5.99\n3.59\n19 ml"
  },
  {
    "raw_text": "Ambi Pur Luchtverfrisser spray fris linnen\n\n40% kortingvanaf maandag\n\n4.49\n2.69\n185 ml"
  },
  {
    "raw_text": "HG Afvoerreiniger badkamer\n4.69\n6 stuks"
  },
  {
    "raw_text": "Robijn Wasverzachter kokos\n\n3 voor 9.00vanaf maandag\n\n7.29\n38 wasbeurten"
  },
  {
    "raw_text": "AH Microvezel dweil\n2.49\nper stuk"
  },
  {
    "raw_text": "Persil Deep clean waspoeder megaperls kleur\n\n1 + 1 GRATISvandaag\n\n10.69\n17 wasbeurten"
  },
  {
    "raw_text": "Vileda Schuursponsen Slalom Soft 2-Pack\n2.99\n2 stuks"
  },
  {
    "raw_text": "Ecover Afwasmiddel granaatappel & vijg\n\n2e gratisvanaf maandag\n\n3.59\n450 ml"
  },
  {
    "raw_text": "Air Wick Essential mist innerlijke rust navulling\n\n40% kortingvanaf maandag\n\n5.99\n3.59\n20.8 ml"
  },
  {
    "raw_text": "Sorbo Window care raamspons krasvrij\n3.99\n2 stuks"
  },
  {
    "raw_text": "Witte Reus Wellness scents vitality wc-blok\n\n60% kortingvandaag\n\n4.29\n1.72\n50 g"
  },
  {
    "raw_text": "Lenor Wasverzachter katoen\n\n3 VOOR 14.99vandaag\n\n9.99\n55 wasbeurten"
  },
  {
    "raw_text": "Nalys keuken- en toiletpapier pakket\n\nonlinePakketkortingvandaag\n\n9.48\n4.74\nper pakket"
  },
  {
    "raw_text": "Dreft 3in1 power spray + navulling lemon\n\n2e gratisvanaf maandag\n\n12.99\n1 l"
  },
  {
    "raw_text": "HG Parketreiniger\n8.99\n1 l"
  },
  {
    "raw_text": "Ecover Wasmiddel universal vloeibaar navulling\n\n2e Halve Prijsvandaag\n\n44.99\n100 wasbeurten"
  },
  {
    "raw_text": "HG Eco kalkverwijderaar\n5.79\n0,5 l"
  },
  {
    "raw_text": "AH 3-in-1 Antikalk powergel\n3.29\n0,75 l"
  },
  {
    "raw_text": "Witte Reus Toiletblok kracht actief oceaan\n\n60% kortingvandaag\n\n9.99\n4.00\n150 g"
  },
  {
    "raw_text": "K2r Machine reiniger\n3.49\n2 wasbeurten"
  },
  {
    "raw_text": "Sorbo Bathroom wonder anti-kalk doek\n4.99\n2 stuks"
  },
  {
    "raw_text": "Dettol Wasmachine reiniger duo\n\n30% kortingvanaf maandag\n\n7.69\n5.38\n2 wasbeurten"
  },
  {
    "raw_text": "Sun Vaatwascapsules 2-pack\n\nonline30% volume voordeelvandaag\n\n39.18\n27.43\n2 stuks"
  },
  {
    "raw_text": "HG Tapijtreiniger\n7.79\n0,5 l"
  },
  {
    "raw_text": "Blue Wonder Oven, grill & BBQ reiniger spray\n4.19\n0,5 l"
  },
  {
    "raw_text": "Blixer Stofzuigerzak verfrisser\n1.69\nper stuk"
  },
  {
    "raw_text": "Greenminds Badstof vaatdoeken\n3.99\n2 stuks"
  },
  {
    "raw_text": "AH Toiletblok dennen navulling\n2.19\n4 stuks"
  },
  {
    "raw_text": "AH Geureditie zeemineraal & cederhout navul\n1.49\n24 ml"
  },
  {
    "raw_text": "Ecover Allesreiniger citroengras gember navul\n\n2e gratisvanaf maandag\n\n13.99\n5 l"
  },
  {
    "raw_text": "Sorbo Dust magnet stofwisser\n5.19\nper stuk"
  },
  {
    "raw_text": "HG Roestvrijstaal snel reiniger\n9.09\n300 ml"
  },
  {
    "raw_text": "HG Spray tegen zilvervisjes\n17.29\n400 ml"
  },
  {
    "raw_text": "AH Viscose mop\n1.99\nper stuk"
  },
  {
    "raw_text": "HG Airfryer reiniger\n11.99\n250 ml"
  },
  {
    "raw_text": "Glade Automatic spray relaxing zen navulling\n\n40% kortingvanaf maandag\n\n6.19\n3.71\n269 ml"
  },
  {
    "raw_text": "HG Brilreiniger\n6.49\n125 ml"
  },
  {
    "raw_text": "The Green Lab Co. Keukenreiniger tablet eucalyptus\n4.95\n3 stuks"
  },
  {
    "raw_text": "Ajax Eucalyptus spray navulling\n2.99\n0,75 l"
  },
  {
    "raw_text": "Ambi Pur Car luchtverfrisser zeebries\n\n40% kortingvanaf maandag\n\n2.99\n1.79\n2 ml"
  },
  {
    "raw_text": "Ariel Vlekverwijderaar spray gold\n\n2e gratisvanaf maandag\n\n9.99\n0,75 l"
  },
  {
    "raw_text": "Brasso Koperglans\n5.99\n175 ml"
  },
  {
    "raw_text": "HG Koffiemachine ontkalker melkzuur\n9.29\n0,5 l"
  },
  {
    "raw_text": "AH Antikalk tabletten 3 in 1\n4.79\n50 wasbeurten"
  },
  {
    "raw_text": "Persil Deep clean 4 in 1 discs capsules kleur\n\n1 + 1 GRATISvandaag\n\n10.99\n15 wasbeurten"
  },
  {
    "raw_text": "Ambi Pur Ap wc tri-gel rose & lily\n3.89\n45 g"
  },
  {
    "raw_text": "AH kalkreiniger spray & navul pakket\n\nonlinePakket\n\n4.18\n2 stuks"
  },
  {
    "raw_text": "Ariel Pods color the big one wascapsules\n\n1 + 1 GRATISvandaag\n\n29.99\n25 wasbeurten"
  },
  {
    "raw_text": "Nalys keukenpapier pakket\n\nonlinePakketkortingvandaag\n\n7.88\n3.94\nper pakket"
  },
  {
    "raw_text": "Ambi Pur 3volution fris linnen navulling\n\n40% kortingvanaf maandag\n\n11.99\n7.19\n40 ml"
  },
  {
    "raw_text": "HG Op-reis-wasje\n3.99\n200 ml"
  },
  {
    "raw_text": "HG Natuursteenreiniger glans\n14.19\n1 l"
  },
  {
    "raw_text": "Blue Wonder Natuurlijke allesreiniger\n4.55\n0,75 l"
  },
  {
    "raw_text": "Calgon Hygine+ wasmachinereiniger en anti kalk\n8.79\n17 wasbeurten"
  },
  {
    "raw_text": "Ecover Wasverzachter rose\n\n2e Halve Prijsvandaag\n\n4.89\n33 wasbeurten"
  },
  {
    "raw_text": "Greenminds Schuursponzen\n2.59\n2 stuks"
  },
  {
    "raw_text": "Frisse Reus Wasmiddel vloeibaar gel orchidee\n\n1 + 1 GRATISvandaag\n\n21.98\n77 wasbeurten"
  },
  {
    "raw_text": "Air Wick Neutraliserende luchtverfrisser spray\n\n40% kortingvanaf maandag\n\n4.29\n2.57\n237 ml"
  },
  {
    "raw_text": "Nibro Strijkspray\n3.19\n400 ml"
  },
  {
    "raw_text": "AH Natuurzeem\n7.99\nper stuk"
  },
  {
    "raw_text": "HG Hygiënische matras opfrisser\n7.89\n500 ml"
  },
  {
    "raw_text": "Calgon Wasmachinereiniger en anti kalk\n8.99\n0,75 l"
  },
  {
    "raw_text": "AH Spray geureditie jasmijn & citrus\n1.79\n12 ml"
  },
  {
    "raw_text": "Seepje Waszeep bergamot en limoengras\n\n2e gratisvanaf maandag\n\n4.99\nper stuk"
  },
  {
    "raw_text": "Air Wick Elektrische luchtverfrisser starterkit\n\n40% kortingvanaf maandag\n\n7.49\n4.49\n19 ml"
  },
  {
    "raw_text": "Ambi Pur Wc active tri-gel wild hibiscus\n3.89\n45 g"
  },
  {
    "raw_text": "Ariel Vloeibaar+ ultra wasmiddel\n\n1 + 1 GRATISvandaag\n\n23.99\n30 wasbeurten"
  },
  {
    "raw_text": "Antikal Original gel kalkreiniger\n4.99\n0,75 l"
  },
  {
    "raw_text": "Ambi Pur 3volution fris linnen starterkit\n\n40% kortingvanaf maandag\n\n8.39\n5.03\n20 ml"
  },
  {
    "raw_text": "HG Kalkweg concentraat\n7.89\n0,5 l"
  },
  {
    "raw_text": "Ambi Pur Toiletblok water-mint navulling\n5.89\n165 ml"
  },
  {
    "raw_text": "4711 Colognette lemon\n\n30% kortingvandaag\n\n3.75\n2.62\n20 stuks"
  },
  {
    "raw_text": "HG Kunststofreiniger glans\n9.29\n1 l"
  },
  {
    "raw_text": "HG Terrastegelreiniger\n9.29\n1 l"
  },
  {
    "raw_text": "Vileda Magic spongidou soft 3-pack\n2.99\n3 stuks"
  },
  {
    "raw_text": "Persil Deep clean wasmiddel capsules universal\n\n1 + 1 GRATISvandaag\n\n10.99\n15 wasbeurten"
  },
  {
    "raw_text": "HG Fruitvliegjesval navulling\n9.29\n2 x 20 ml"
  },
  {
    "raw_text": "Dreft Waspoeder the ultimate care colour\n7.99\n16 wasbeurten"
  },
  {
    "raw_text": "Ambi Pur Ap wc tri-gel water flow\n3.89\n45 g"
  },
  {
    "raw_text": "Sorbo Recycled microvezeldoekjes\n4.99\nper stuk"
  },
  {
    "raw_text": "Air Wick Neutraliserende luchtverfrisser spray\n\n40% kortingvanaf maandag\n\n4.29\n2.57\n237 ml"
  },
  {
    "raw_text": "Ambi Pur Wc active tri-gel wild blue blossom\n3.89\n45 g"
  },
  {
    "raw_text": "Toppits IJsblokzakjes\n1.79\n10 stuks"
  },
  {
    "raw_text": "Bruynzeel Spiegel & glasreiniger anti condensspray\n4.99\n0,5 l"
  },
  {
    "raw_text": "HG Power gel brush oven\n8.29\n250 ml"
  },
  {
    "raw_text": "The Green Lab Co. Badkamerreiniger tablet lavendel\n4.95\n3 stuks"
  },
  {
    "raw_text": "The Green Lab Co. Glasreiniger tablet munt\n4.95\n3 stuks"
  },
  {
    "raw_text": "Dettol Allesreiniger katoen\n\n30% kortingvanaf maandag\n\n6.59\n4.61\n2 l"
  },
  {
    "raw_text": "Air Wick Elektrische navulling huisdier katoen\n\n40% kortingvanaf maandag\n\n5.99\n3.59\n19 ml"
  },
  {
    "raw_text": "Glade Luchtverfrisser spray muguet\n\n40% kortingvanaf maandag\n\n2.19\n1.31\n300 ml"
  },
  {
    "raw_text": "Ecover Afwasmiddel kamille & clementine\n\n2e gratisvanaf maandag\n\n3.59\n450 ml"
  },
  {
    "raw_text": "Ecover Delicate zero\n\n2e Halve Prijsvandaag\n\n8.29\n22 wasbeurten"
  },
  {
    "raw_text": "Dreft Ultimate care wasmiddel deli & wool\n10.99\n21 wasbeurten"
  },
  {
    "raw_text": "Frisse Reus Wasmiddel vloeibaar gel lotus amandel\n\n1 + 1 GRATISvandaag\n\n21.98\n77 wasbeurten"
  },
  {
    "raw_text": "Everdrop Badkamerreiniger navulling\n3.19\nper stuk"
  },
  {
    "raw_text": "Kleenex Balsam & UltraSoft tissue Pakket\n\nonline10% pakketkorting\n\n6.97\n6.27\nper pakket"
  },
  {
    "raw_text": "HG Power foam douche\n8.09\n300 ml"
  },
  {
    "raw_text": "Swiffer Vloerdoekjes droog navulling big pack\n15.99\n52 stuks"
  },
  {
    "raw_text": "Ecover Wasmiddel zero\n\n2e Halve Prijsvandaag\n\n14.39\n28 wasbeurten"
  },
  {
    "raw_text": "HG Laminaatreiniger glans\n10.69\n1 l"
  },
  {
    "raw_text": "Swiffer Vloerreiniger starterset\n17.39\nper set"
  },
  {
    "raw_text": "HG Stofzuigerlucht verfrisser\n8.69\n180 g"
  },
  {
    "raw_text": "HG Spray tegen muggen en vliegen\n13.29\n400 ml"
  },
  {
    "raw_text": "Persil Deep clean waspoeder megaperls universal\n\n1 + 1 GRATISvandaag\n\n10.69\n17 wasbeurten"
  },
  {
    "raw_text": "Dubro Antikalk hygiene spray\n3.99\n0,65 l"
  },
  {
    "raw_text": "Glade Electric scented sandelwood navulling\n\n40% kortingvanaf maandag\n\n5.69\n3.41\n20 ml"
  },
  {
    "raw_text": "Sorbo Kitchen wonder keukendoek\n4.99\n2 stuks"
  },
  {
    "raw_text": "Swirl Pedaalemmerzak met handvat 20liter\n3.99\n6 stuks"
  },
  {
    "raw_text": "Air Wick Elektrische luchtverfrisser navulling\n\n40% kortingvanaf maandag\n\n5.99\n3.59\n19 ml"
  },
  {
    "raw_text": "Ecover Wasmiddel color vloeibaar navulling\n\n2e Halve Prijsvandaag\n\n44.99\n100 wasbeurten"
  },
  {
    "raw_text": "Bruynzeel Schimmel & Aanslagreiniger\n8.29\n0,5 l"
  },
  {
    "raw_text": "Ecover Wascapsules universal\n\n2e Halve Prijsvandaag\n\n12.99\n18 wasbeurten"
  },
  {
    "raw_text": "Everdrop Toiletreiniger starter set\n5.99\nper stuk"
  },
  {
    "raw_text": "Ambi Pur Car luchtverfrisser vanille boeket\n\n40% kortingvanaf maandag\n\n2.99\n1.79\n2 ml"
  },
  {
    "raw_text": "Ariel Big one color\n\nonline35% Op=Op kortingvandaag\n\n22.99\n14.94\n18 wasbeurten"
  },
  {
    "raw_text": "Glade Sense & spray relaxing zen navulling\n\n40% kortingvanaf maandag\n\n5.49\n3.29\n18 ml"
  },
  {
    "raw_text": "HG Tegelreiniger glans\n10.59\n1 l"
  },
  {
    "raw_text": "Glade Sense & spray sandalwood navulling\n\n40% kortingvanaf maandag\n\n5.49\n3.29\n18 ml"
  },
  {
    "raw_text": "HG Leerreiniger\n9.29\n300 ml"
  },
  {
    "raw_text": "Glade Sense & spray pure clean linen navul\n\n40% kortingvanaf maandag\n\n5.49\n3.29\n18 ml"
  },
  {
    "raw_text": "Glade Automatic spray houder pure clean linen\n\n40% kortingvanaf maandag\n\n8.99\n5.39\n269 ml"
  },
  {
    "raw_text": "Greenminds Huishouddoekjes\n2.49\n3 stuks"
  },
  {
    "raw_text": "Seepje Vaste afwaszeep tintelfrisse limoen\n\n2e gratisvanaf maandag\n\n3.79\nper stuk"
  },
  {
    "raw_text": "Everdrop Keukrenreiniger navulling\n3.19\nper stuk"
  },
  {
    "raw_text": "Everdrop Allesreiniger cleaner navulling\n3.19\nper stuk"
  },
  {
    "raw_text": "Sorbo Kitchen pad keukenspons\n3.49\nper stuk"
  },
  {
    "raw_text": "AH wasmiddel kleur pakket\n\nonlinePakket\n\n8.48\nper pakket"
  },
  {
    "raw_text": "Ariel Vlekverwijderaar spray delicate & wool\n\n2e gratisvanaf maandag\n\n9.99\n0,75 l"
  },
  {
    "raw_text": "Nalys keuken & toiletpapier pakket\n\nonlinePakketkortingvandaag\n\n11.48\n5.74\nper pakket"
  },
  {
    "raw_text": "Glade Sense & spray exotic blossoms navulling\n\n40% kortingvanaf maandag\n\n5.49\n3.29\n18 ml"
  },
  {
    "raw_text": "Persil Deep clean 4 in 1 discs capsules kleur\n\n1 + 1 GRATISvandaag\n\n16.99\n24 wasbeurten"
  },
  {
    "raw_text": "Bruynzeel Meubelolie\n4.29\n200 ml"
  },
  {
    "raw_text": "AH allesreiniger citrus pakket\n\nonlinePakket\n\n3.88\nper pakket"
  },
  {
    "raw_text": "Ariel 4in1 pods+ black wasmiddelcapsules\n\n1 + 1 GRATISvandaag\n\n15.99\n15 wasbeurten"
  },
  {
    "raw_text": "HG Parketreiniger glans\n11.99\n1 l"
  },
  {
    "raw_text": "Glade Sense & spray ocean adventure navulling\n\n40% kortingvanaf maandag\n\n5.49\n3.29\n18 ml"
  },
  {
    "raw_text": "Glade Sense & spray vanilla blossom navulling\n\n40% kortingvanaf maandag\n\n5.49\n3.29\n18 ml"
  },
  {
    "raw_text": "Destop Wasmachinereiniger integrale behandeling\n4.19\n250 ml"
  },
  {
    "raw_text": "Dreft Ultimate care wasmiddel colour\n10.99\n21 wasbeurten"
  },
  {
    "raw_text": "Air Wick Elektrische navulling lavendel\n\n40% kortingvanaf maandag\n\n5.99\n3.59\n19 ml"
  },
  {
    "raw_text": "Glade Electric scented oil houder relaxing zen\n\n40% kortingvanaf maandag\n\n6.19\n3.71\n20 ml"
  },
  {
    "raw_text": "HG Tegelreiniger extra sterk\n16.79\n1 l"
  },
  {
    "raw_text": "Bruynzeel Vlekkenspray voor tapijt & bekleding\n8.29\n0,5 l"
  },
  {
    "raw_text": "Dr. Beckmann Active white oxi vlekverwijderaar\n6.99\n400 g"
  },
  {
    "raw_text": "HG Power gel brush kalk\n8.29\n250 ml"
  },
  {
    "raw_text": "Everdrop Badkamerreiniger starter set\n4.29\nper stuk"
  },
  {
    "raw_text": "AH allesreiniger bloemen & fruit pakket\n\nonlinePakket\n\n3.88\nper pakket"
  },
  {
    "raw_text": "Air Wick Automatische luchtverfrisser lavendel\n\n40% kortingvanaf maandag\n\n11.99\n7.19\n20 ml"
  },
  {
    "raw_text": "Ariel Pods color the big one wascapsules\n\n1 + 1 GRATISvandaag\n\n19.99\n15 wasbeurten"
  },
  {
    "raw_text": "Robijn Quickwash sunset bloom wasmiddel\n\nNieuw\n\n18.99\n22 wasbeurten"
  },
  {
    "raw_text": "Glade Sense & spray lavender navulling\n\n40% kortingvanaf maandag\n\n5.49\n3.29\n18 ml"
  },
  {
    "raw_text": "HG Meubelhersteller donker hout\n11.19\n250 ml"
  },
  {
    "raw_text": "HG Waterdicht katoen, linnen, wol, meng\n6.79\n300 ml"
  },
  {
    "raw_text": "HG X spray tegen ongedierte\n15.79\n400 ml"
  },
  {
    "raw_text": "Ecover Ontvlekker\n\n2e gratisvanaf maandag\n\n5.49\n200 ml"
  },
  {
    "raw_text": "Glade Electric scented oil relax zen navulling\n\n40% kortingvanaf maandag\n\n5.69\n3.41\n20 ml"
  },
  {
    "raw_text": "Bruynzeel Sanitair sprayreiniger\n4.99\n0,5 l"
  },
  {
    "raw_text": "Bruynzeel Allesreinigerspray\n4.99\n0,5 l"
  },
  {
    "raw_text": "Ecover Afwasmiddel kamille & clementine\n\n2e gratisvanaf maandag\n\n5.69\n0,95 l"
  },
  {
    "raw_text": "AH wasmiddel zwart pakket\n\nonlinePakket\n\n8.48\nper pakket"
  },
  {
    "raw_text": "AH wasmiddel wit pakket\n\nonlinePakket\n\n8.48\nper pakket"
  },
  {
    "raw_text": "Ajax Spray & navulling eucalyptus pakket\n\nonline20% pakketkorting\n\n6.48\n5.18\nper stuk"
  },
  {
    "raw_text": "Ariel Pods original the big one wascapsules\n\n1 + 1 GRATISvandaag\n\n19.99\n15 wasbeurten"
  },
  {
    "raw_text": "Ariel 4in1 pods+ black wasmiddelcapsules\n\n1 + 1 GRATISvandaag\n\n26.49\n26 wasbeurten"
  },
  {
    "raw_text": "HG Schimmel beschermer\n11.79\n0,5 l"
  },
  {
    "raw_text": "Robijn Quickwash spring blossom wasmiddel\n\nNieuw\n\n18.99\n22 wasbeurten"
  },
  {
    "raw_text": "Vanish vlekverwijderaar poeder pakket\n\nonlinePakketkortingvandaag\n\n17.98\n8.99\nper pakket"
  },
  {
    "raw_text": "HG Meubelhersteller licht hout\n11.19\n250 ml"
  },
  {
    "raw_text": "Glade Sense & spray relaxing starterkit\n\n40% kortingvanaf maandag\n\n8.29\n4.97\n18 ml"
  },
  {
    "raw_text": "Ecover Wasverzachter appelbloesem navulling\n\n2e Halve Prijsvandaag\n\n21.49\n166 wasbeurten"
  },
  {
    "raw_text": "Glade Automatic spray tranquil navulling\n\n40% kortingvanaf maandag\n\n6.19\n3.71\n269 ml"
  },
  {
    "raw_text": "Bruynzeel Hout onderhoudspray\n6.29\n0,5 l"
  },
  {
    "raw_text": "Bruynzeel Keuken sprayreiniger\n4.99\n0,5 l"
  },
  {
    "raw_text": "Everdrop Keukenreiniger starter set\n4.29\nper stuk"
  },
  {
    "raw_text": "Page Schoon Pakket\n\nonline15% pakketkorting\n\n9.88\n8.40\nper stuk"
  },
  {
    "raw_text": "AH keukenreiniger pakket\n\nonlinePakket\n\n4.18\nper pakket"
  },
  {
    "raw_text": "AH badkamereiniger pakket\n\nonlinePakket\n\n4.18\nper pakket"
  },
  {
    "raw_text": "Glade Electric scented oil refill linen\n\n40% kortingvanaf maandag\n\n5.69\n3.41\n20 ml"
  },
  {
    "raw_text": "Ariel 4in1 pods+ unstoppables wasmiddelcapsule\n\n1 + 1 GRATISvandaag\n\n15.99\n15 wasbeurten"
  },
  {
    "raw_text": "Robijn Quickwash morning dew wasmiddel\n\nNieuw\n\n18.99\n22 wasbeurten"
  },
  {
    "raw_text": "Vapona Vliegenvangers\n3.49\n4 stuks"
  },
  {
    "raw_text": "AH Stofzuigerzakken type Philips/Oslo\n4.99\n4 stuks"
  },
  {
    "raw_text": "Super Ninja Zilvervisjesvallen\n5.99\n3 stuks"
  },
  {
    "raw_text": "Ecover Afwasmiddel citroen aloë vera navulling\n\n2e gratisvanaf maandag\n\n21.79\n5 l"
  },
  {
    "raw_text": "Dreft Ultimate care wasmiddel morning fresh\n10.99\n21 wasbeurten"
  },
  {
    "raw_text": "Sorbo Kitchen scrub cloth keukendoek\n3.79\nper stuk"
  },
  {
    "raw_text": "Bruynzeel Antikalkschuim reiniger foam\n7.29\n0,5 l"
  },
  {
    "raw_text": "Ecover Vloeibaar wasmiddel wol & fijnwas navul\n\n2e Halve Prijsvandaag\n\n35.99\n5 l"
  },
  {
    "raw_text": "Dr. Beckmann Active colour oxi vlekverwijderaar\n6.99\n400 g"
  },
  {
    "raw_text": "Ariel 4in1 pods+ ultra wasmiddelcapsules\n\n1 + 1 GRATISvandaag\n\n26.49\n26 wasbeurten"
  },
  {
    "raw_text": "Ariel 4in1 pods+ active wasmiddelcapsules\n\n1 + 1 GRATISvandaag\n\n15.99\n15 wasbeurten"
  },
  {
    "raw_text": "Vapona Anti mug navulling 45 nachten\n8.49\nper stuk"
  }
]