[
  {
    "n": "Naaimachine - Tradition 4.5/5 (48) SINGER 139.-",
    "p": "",
    "o": "Naaimachine 2282L - Tradition Naaimachine 2282L - Tradition 139.-",
    "s": "2282L",
    "l": "https://www.lidl.nl/assets/gcp6a6d31fb79f643078cd56fca8bb255c0.jpg"
  },
  {
    "n": "Naaimachine Serenade met LCDscherm 3.9/5 (61) SINGER Adviesprijs: 369.- * 199.-",
    "p": "",
    "o": "Naaimachine 660L Serenade met LCD-scherm Naaimachine 660L Serenade met LCD-scherm Adviesprijs: 369.- * 199.-",
    "s": "660L",
    "l": "https://www.lidl.nl/assets/gcpf4fefa0508fc4fb99a9cb4126d213f27.jpg"
  },
  {
    "n": "Overlockmachine S010 4.2/5 (38) SINGER",
    "p": "",
    "o": "Adviesprijs: 469.- * 179.-",
    "s": "",
    "l": "https://www.lidl.nl/assets/gcpe9364835505c40b986083669bb602241.jpg"
  },
  {
    "n": "Handnaaimachine SINGER",
    "p": "9.99",
    "o": "-50%",
    "s": "",
    "l": "https://www.lidl.nl/assets/gcp6ebad6f5266147a19db22bd6393b1b00.jpg"
  },
  {
    "n": "Naaimachine C5605 5/5 (1) SINGER",
    "p": "",
    "o": "Adviesprijs: 349.- * 249.-",
    "s": "",
    "l": "https://www.lidl.nl/assets/gcp4b2b73acaa56411b9de66e8ed8d90e44.jpg"
  },
  {
    "n": "Naaimachine M3205 4/5 (2) SINGER",
    "p": "",
    "o": "Adviesprijs: 279.- * 179.-",
    "s": "",
    "l": "https://www.lidl.nl/assets/gcp71014a6c48814d638008babdcb931d9f.jpg"
  },
  {
    "n": "Compacte naaimachine EASYmaxx Adviesprijs: *",
    "p": "49.99",
    "o": "",
    "s": "",
    "l": "https://www.lidl.nl/assets/gcp97d84e04adf94bd9af83de07226e7c68.jpg"
  },
  {
    "n": "IJsblokjesmachine 4/5 (49) SILVERCREST® KITCHEN TOOLS",
    "p": "",
    "o": "199.- -10% 179.-",
    "s": "",
    "l": "https://www.lidl.nl/assets/gcpb206e5898aa048acbf2fc36c9552aa02.jpeg"
  },
  {
    "n": "IJsblokjesmachine 4/5 (10) SILVERCREST® KITCHEN TOOLS",
    "p": "",
    "o": "159.-",
    "s": "",
    "l": "https://www.lidl.nl/assets/gcp105b19aa97114280ad13ae2b57408482.jpeg"
  },
  {
    "n": "IJsblokjesmachine 4.7/5 (346) SILVERCREST® KITCHEN TOOLS",
    "p": "79.99",
    "o": "",
    "s": "",
    "l": "https://www.lidl.nl/assets/gcp1faa0b53a5ec4d298f440cd54962107d.jpg"
  },
  {
    "n": "Minikoelkast SILVERCREST® KITCHEN TOOLS",
    "p": "59.99",
    "o": "",
    "s": "",
    "l": "https://www.lidl.nl/assets/gcp9dc48176e7174012abf69f7a069aedcc.jpg"
  },
  {
    "n": "Elektrische koelbox 4.7/5 (610) CRIVIT Productgegevensblad",
    "p": "59.99",
    "o": "",
    "s": "",
    "l": "https://www.lidl.nl/assets/gcpc470d06393ee4490a913759500a6963f.jpg"
  },
  {
    "n": "Elektrische koelbox 4.7/5 (610) CRIVIT Productgegevensblad",
    "p": "59.99",
    "o": "",
    "s": "",
    "l": "https://www.lidl.nl/assets/gcpc470d06393ee4490a913759500a6963f.jpg"
  },
  {
    "n": "Premium CashmereFeeling deken Beste beoordelingen 4.8/5 (736) Gözze vanaf",
    "p": "34.14",
    "o": "Premium Cashmere-Feeling deken Premium Cashmere-Feeling deken vanaf",
    "s": "",
    "l": "https://www.lidl.nl/assets/8e12876c8f42cf80747fdb8d36bf30f9.jpeg"
  },
  {
    "n": "Baby knuffeldeken, 70 x 100 cm (Lichtgrijs) 4.6/5 (24) bellybutton Adviesprijs: *",
    "p": "16.99",
    "o": "",
    "s": "70 X 100 CM (LICHTGRIJS) 4.6/5 (24) BELLYBUTTON BABY KNUFFELDEKEN, 70 X 100 CM (LICHTGRIJS) ADVIESPRIJS: 59.95 * 16.99",
    "l": "https://www.lidl.nl/assets/gcpce03968d80a14ae7bf1e8dff2fbf805a.jpeg"
  },
  {
    "n": "Woondeken 200 x 220 cm 5/5 (5) LIVARNO home",
    "p": "19.99",
    "o": "",
    "s": "200 X 220 CM 5/5 (5) LIVARNO HOME WOONDEKEN 200 X 220 CM 19.99",
    "l": "https://www.lidl.nl/assets/gcp03e41513c0b34ed5aebb8af5443f7857.jpeg"
  },
  {
    "n": "Plaid 150 x 200 cm 5/5 (5) LIVARNO home",
    "p": "14.99",
    "o": "-25%",
    "s": "150 X 200 CM 5/5 (5) LIVARNO HOME PLAID 150 X 200 CM 19.99 -25% 14.99",
    "l": "https://www.lidl.nl/assets/gcpb19b247dfd9c4b0da01b13759fde6bb4.jpg"
  },
  {
    "n": "Picknickkleed 125 x 160 cm 4.3/5 (7)",
    "p": "8.99",
    "o": "",
    "s": "125 X 160 CM 4.3/5 (7) PICKNICKKLEED 125 X 160 CM 8.99",
    "l": "https://www.lidl.nl/assets/gcp23e937e596114d58ad1bd6bdfad3fb2a.jpeg"
  },
  {
    "n": "Teddy fleecedeken 150 x 200 cm 3.7/5 (11) LIVARNO home",
    "p": "20.99",
    "o": "",
    "s": "150 X 200 CM 3.7/5 (11) LIVARNO HOME TEDDY FLEECEDEKEN 150 X 200 CM 20.99",
    "l": "https://www.lidl.nl/assets/gcp88f629574d784c6f86434cfa68c24062.jpeg"
  },
  {
    "n": "Plaid 150 x 200 cm 5/5 (3) SANSIBAR",
    "p": "29.99",
    "o": "",
    "s": "150 X 200 CM 5/5 (3) SANSIBAR PLAID 150 X 200 CM 29.99",
    "l": "https://www.lidl.nl/assets/gcp5fca990ed1c94ea2b2f524597419285f.jpg"
  },
  {
    "n": "Deken voor kinderen 5/5 (2) LIVARNO home",
    "p": "5.99",
    "o": "",
    "s": "",
    "l": "https://www.lidl.nl/assets/gcp6b60152b6aaf493c99f5baf664ee7c3e.jpg"
  },
  {
    "n": "Plaid 125 x 140 cm 3.7/5 (3) LIVARNO home",
    "p": "9.99",
    "o": "-23%",
    "s": "125 X 140 CM 3.7/5 (3) LIVARNO HOME PLAID 125 X 140 CM 12.99 -23% 9.99",
    "l": "https://www.lidl.nl/assets/gcp2de77266ca744169840865cf30abe8c0.jpeg"
  },
  {
    "n": "Plaid 200 x 220 cm LIVARNO home",
    "p": "5.99",
    "o": "-50%",
    "s": "200 X 220 CM LIVARNO HOME PLAID 200 X 220 CM 11.99 -50% 5.99",
    "l": "https://www.lidl.nl/assets/gcpd7b7701c723c4028a456694a4350d6a3.jpg"
  },
  {
    "n": "Plaid 130 x 170 cm 3/5 (5) LIVARNO home",
    "p": "6.99",
    "o": "",
    "s": "130 X 170 CM 3/5 (5) LIVARNO HOME PLAID 130 X 170 CM 6.99",
    "l": "https://www.lidl.nl/assets/gcp0553aabba5974eb0900346bf81208777.jpg"
  },
  {
    "n": "Sprei met ruches LIVARNO home",
    "p": "17.99",
    "o": "",
    "s": "",
    "l": "https://www.lidl.nl/assets/gcp17154a22053846b3be46cc2bedd1bb55.jpg"
  },
  {
    "n": "Plaid 150 x 200 cm 5/5 (1) LIVARNO home",
    "p": "5.99",
    "o": "-50%",
    "s": "150 X 200 CM 5/5 (1) LIVARNO HOME PLAID 150 X 200 CM 11.99 -50% 5.99",
    "l": "https://www.lidl.nl/assets/gcp98fe88c2d2ac46c189ffa72a0039ac1d.jpg"
  },
  {
    "n": "Woondeken MAGMA",
    "p": "49.90",
    "o": "",
    "s": "",
    "l": "https://www.lidl.nl/assets/5bbd4ddd84826055477735f557e5c2aa.jpeg"
  },
  {
    "n": "Plaid 130 x 170 cm LIVARNO home",
    "p": "5.99",
    "o": "",
    "s": "130 X 170 CM LIVARNO HOME PLAID 130 X 170 CM 5.99",
    "l": "https://www.lidl.nl/assets/gcp552b185b6be1490d83dca6a9b3e6922e.jpg"
  },
  {
    "n": "Plaid 180 x 240 cm LIVARNO home",
    "p": "24.99",
    "o": "",
    "s": "180 X 240 CM LIVARNO HOME PLAID 180 X 240 CM 24.99",
    "l": "https://www.lidl.nl/assets/gcpedbed477d7e64e699f08c1806fcd6190.jpg"
  },
  {
    "n": "Plaid 150 x 250 cm LIVARNO home",
    "p": "13.99",
    "o": "",
    "s": "150 X 250 CM LIVARNO HOME PLAID 150 X 250 CM 13.99",
    "l": "https://www.lidl.nl/assets/gcp2d0aa7d04aa84537b8182e5fc9aa567e.jpg"
  },
  {
    "n": "Radiator droogrek 4.5/5 (86) LIVARNO home",
    "p": "5.99",
    "o": "Tip van Lidl",
    "s": "",
    "l": "https://www.lidl.nl/assets/gcpdd0ffbd08c294717b98bdb11e81bd5d4.jpg"
  },
  {
    "n": "Droogrek Beste beoordelingen 4.9/5 (8) LIVARNO home",
    "p": "9.99",
    "o": "-33%",
    "s": "",
    "l": "https://www.lidl.nl/assets/gcp456a8e1b32124ae2a35ee63feacc1740.jpg"
  },
  {
    "n": "Droogrek 4/5 (12) LIVARNO home",
    "p": "19.99",
    "o": "-42%",
    "s": "",
    "l": "https://www.lidl.nl/assets/gcp4e37ab7fc52047ab81bdf5236ca1276e.jpg"
  },
  {
    "n": "Droogrek 4.5/5 (15) LIVARNO home",
    "p": "39.99",
    "o": "",
    "s": "",
    "l": "https://www.lidl.nl/assets/gcpf3ea770b06f445d585e5fa8f6ee996ca.jpg"
  },
  {
    "n": "Radiatordroogrek 4.5/5 (15) Vileda Adviesprijs: *",
    "p": "4.99",
    "o": "",
    "s": "",
    "l": "https://www.lidl.nl/assets/gcp832d7137fb5a4df194e7aa0f6b7ec1a7.jpeg"
  },
  {
    "n": "Dubbele waslijn Beldray",
    "p": "12.99",
    "o": "-35%",
    "s": "",
    "l": "https://www.lidl.nl/assets/gcp293fcb5b69c0464bbd2a180335622b81.jpg"
  },
  {
    "n": "Droogmolen SUNLIFT 50M 5/5 (3) Vileda",
    "p": "92.50",
    "o": "Droogmolen SUN-LIFT 50M Droogmolen SUN-LIFT 50M",
    "s": "",
    "l": "https://www.lidl.nl/assets/gcp5ce08adf0a6a483885b14e4b66a83d04.jpeg"
  },
  {
    "n": "Inklapbaar droogrek 4.4/5 (8) Weinberger Adviesprijs: *",
    "p": "9.99",
    "o": "",
    "s": "",
    "l": "https://www.lidl.nl/assets/gcpf51dae0e7559492a80f7272d098c26a0.jpg"
  },
  {
    "n": "Wasrek Universal 4.5/5 (4) Vileda",
    "p": "29.99",
    "o": "",
    "s": "",
    "l": "https://www.lidl.nl/assets/gcpae3854a8e4e54852a72402907bec143c.jpeg"
  },
  {
    "n": "Droogrek 10 m 3.2/5 (10) LIVARNO home",
    "p": "8.99",
    "o": "-35%",
    "s": "",
    "l": "https://www.lidl.nl/assets/gcp814b46cafdba47169c607b48da652fc9.jpg"
  },
  {
    "n": "Droogrek Vileda Adviesprijs: *",
    "p": "19.99",
    "o": "",
    "s": "",
    "l": "https://www.lidl.nl/assets/gcp1787d860dc5a414d8540b15de59085e2.jpeg"
  },
  {
    "n": "Droogrek 5/5 (1) Vileda",
    "p": "29.99",
    "o": "-33%",
    "s": "",
    "l": "https://www.lidl.nl/assets/gcp3c4982e9060049aca3998effda16b796.jpg"
  },
  {
    "n": "Droogrek 4/5 (2) LEIFHEIT",
    "p": "7.99",
    "o": "",
    "s": "",
    "l": "https://www.lidl.nl/assets/gcp9ce5b84d4d664ae49e6f346840eca9ce.jpeg"
  },
  {
    "n": "Wasrek STATIC ONE 3.5/5 (2) Vileda",
    "p": "25.99",
    "o": "-35%",
    "s": "",
    "l": "https://www.lidl.nl/assets/gcp40acef4aec574231aad9e6795609f747.jpg"
  },
  {
    "n": "Wasdroger 3/5 (3) LIVARNO home",
    "p": "7.99",
    "o": "",
    "s": "",
    "l": "https://www.lidl.nl/assets/gcp8ca9eae7f6fb48dd8a3f1ef58f6ca50f.jpg"
  },
  {
    "n": "Deur droogrek 3/5 (2) Wenko Adviesprijs: *",
    "p": "56.88",
    "o": "",
    "s": "",
    "l": "https://www.lidl.nl/assets/d3a79b15f5a322b32855bd0d6d87fc20.jpeg"
  },
  {
    "n": "Wasrek Acrobath 1/5 (1) Vileda Adviesprijs: *",
    "p": "19.17",
    "o": "",
    "s": "",
    "l": "https://www.lidl.nl/assets/gcp3a1dc6486ce943699b2bdf962dc7d793.jpeg"
  },
  {
    "n": "Wasrek LinoPop LEIFHEIT Adviesprijs: *",
    "p": "59.99",
    "o": "38.-",
    "s": "",
    "l": "https://www.lidl.nl/assets/gcp4e41dd9db4ee4c50899fdd0f457081d9.jpg"
  },
  {
    "n": "Telescopisch droogrek Wenko",
    "p": "59.99",
    "o": "Tip van Lidl",
    "s": "",
    "l": "https://www.lidl.nl/assets/d5a6ff26c748843eded0966098aa2a9c.jpeg"
  },
  {
    "n": "Wasknijpers 50 Beste beoordelingen 4.8/5 (36) LIVARNO home",
    "p": "6.99",
    "o": "",
    "s": "50 STUKS",
    "l": "https://www.lidl.nl/assets/gcpbdb64c6f8b024d3e84a2043c3452a256.jpg"
  },
  {
    "n": "Wasmand (Rood) 4.6/5 (118) Wenko",
    "p": "39.99",
    "o": "",
    "s": "",
    "l": "https://www.lidl.nl/assets/c1c12a831c15847cdc929d473524e003.jpeg"
  },
  {
    "n": "Wasmand (Mint) Beste beoordelingen 4.8/5 (26) LIVARNO home",
    "p": "6.99",
    "o": "-53%",
    "s": "",
    "l": "https://www.lidl.nl/assets/gcp38f5e1a80b1c4f17933b66a9bf4d84d6.jpg"
  },
  {
    "n": "Wasmand 4.6/5 (23) LIVARNO home",
    "p": "8.99",
    "o": "Tip van Lidl",
    "s": "",
    "l": "https://www.lidl.nl/assets/gcp67ac438d2fc344b29154b2eba0badd12.jpeg"
  },
  {
    "n": "Wasmand Beste beoordelingen 4.8/5 (12) Curver Adviesprijs: *",
    "p": "11.99",
    "o": "",
    "s": "",
    "l": "https://www.lidl.nl/assets/gcp134ffe1c168d4282872f9d3466b6fbab.jpeg"
  },
  {
    "n": "Wasmachine/drogeronderstel (Zwart) 4.3/5 (45) Wenko Adviesprijs: *",
    "p": "73.99",
    "o": "Wasmachine/droger-onderstel (Zwart) Wasmachine/droger-onderstel (Zwart)",
    "s": "",
    "l": "https://www.lidl.nl/assets/gcp8e4c417483ab443786d0dc5ed124c511.jpeg"
  },
  {
    "n": "Wasknijpers 4.6/5 (9) LIVARNO home",
    "p": "0.99",
    "o": "-75%",
    "s": "",
    "l": "https://www.lidl.nl/assets/gcpc6a6051d5a6e4d5d9c730b3977203735.jpeg"
  },
  {
    "n": "Wasmand 4.8/5 (5) Curver Adviesprijs: *",
    "p": "17.99",
    "o": "",
    "s": "",
    "l": "https://www.lidl.nl/assets/gcpc10f420736a9470aa314cd0d0b4df228.jpeg"
  },
  {
    "n": "Bamboe wasmand 4.3/5 (8) Wenko Adviesprijs: *",
    "p": "9.99",
    "o": "",
    "s": "",
    "l": "https://www.lidl.nl/assets/gcp7e04529e9e0c42ea80d5ef4328ca5fee.jpg"
  },
  {
    "n": "Wasmand LIVARNO home",
    "p": "4.95",
    "o": "-17%",
    "s": "",
    "l": "https://www.lidl.nl/assets/gcp796208366a5849f19fdfff78f74773f9.jpg"
  },
  {
    "n": "Opvouwbare wasmand Wenko Adviesprijs: *",
    "p": "8.99",
    "o": "",
    "s": "50 L",
    "l": "https://www.lidl.nl/assets/gcp08e35c3023c3402fb2229acac9dbb903.jpg"
  },
  {
    "n": "Wasmand Corno (Zwart) 3.5/5 (2) Wenko",
    "p": "59.99",
    "o": "",
    "s": "",
    "l": "https://www.lidl.nl/assets/gcp8be4ca3f91d9400f8db53cf233fb3552.jpeg"
  },
  {
    "n": "Ophangbare wasmand LIVARNO home",
    "p": "9.99",
    "o": "",
    "s": "",
    "l": "https://www.lidl.nl/assets/gcp3a83e52adb1a498ba55f4e141462341f.jpg"
  },
  {
    "n": "Wasmachinehoes 1/5 (1) LIVARNO home",
    "p": "2.99",
    "o": "-50%",
    "s": "",
    "l": "https://www.lidl.nl/assets/gcp407ce7f6144d44faab348f8026a24850.jpg"
  },
  {
    "n": "Wasmand Trovo Wenko",
    "p": "53.90",
    "o": "vanaf",
    "s": "",
    "l": "https://www.lidl.nl/assets/f3b4c37dcb5c8ad0909068db4c7e2d5e.jpeg"
  },
  {
    "n": "Droogbollen Wenko",
    "p": "9.99",
    "o": "",
    "s": "",
    "l": "https://www.lidl.nl/assets/gcp3f5fbaddd6bc4e758744cc2e3a01da41.jpg"
  },
  {
    "n": "Reisstrijkijzer 4.5/5 (19) SILVERCREST®",
    "p": "7.99",
    "o": "-46%",
    "s": "",
    "l": "https://www.lidl.nl/assets/gcpeb2f260c56c44e8ca235ec1569ad47fb.jpeg"
  },
  {
    "n": "Stoomstrijkijzer 2000 Series DST2020/30 4.7/5 (18) PHILIPS",
    "p": "23.99",
    "o": "-20%",
    "s": "",
    "l": "https://www.lidl.nl/assets/gcpd335c73b87ba4b30884289f9829ee279.jpeg"
  },
  {
    "n": "Stoomgenerator 4.3/5 (31) SILVERCREST®",
    "p": "49.99",
    "o": "-28%",
    "s": "",
    "l": "https://www.lidl.nl/assets/gcp4c853321d2694f318d87a960f925239c.jpeg"
  },
  {
    "n": "Draadloos stoomstrijkijzer 4.3/5 (149) SILVERCREST®",
    "p": "24.99",
    "o": "",
    "s": "",
    "l": "https://www.lidl.nl/assets/gcp596254e0f7c14a819ef6b034236f7fa0.jpg"
  },
  {
    "n": "Stoomgenerator PSG2000/80 4.2/5 (28) PHILIPS Adviesprijs: *",
    "p": "249.99",
    "o": "69.-",
    "s": "",
    "l": "https://www.lidl.nl/assets/gcp366a8908eb1649b889aea71b6e92eeec.jpeg"
  },
  {
    "n": "Stoomstrijkijzer 4.7/5 (18) SILVERCREST®",
    "p": "24.99",
    "o": "",
    "s": "",
    "l": "https://www.lidl.nl/assets/gcp55d63daeae274871a8961e760999df70.jpg"
  },
  {
    "n": "Stoomstrijkijzer 4.6/5 (28) SILVERCREST®",
    "p": "14.99",
    "o": "",
    "s": "",
    "l": "https://www.lidl.nl/assets/gcp898e386687fe436b8715da8da1de9ae9.jpg"
  },
  {
    "n": "Stoomstrijkijzer DST1030/20 4.1/5 (59) PHILIPS",
    "p": "19.99",
    "o": "",
    "s": "",
    "l": "https://www.lidl.nl/assets/gcpba0fd9686ea94259a61286762b9deaa2.jpeg"
  },
  {
    "n": "Stoomgenerator 4.2/5 (24) SILVERCREST®",
    "p": "89.99",
    "o": "",
    "s": "",
    "l": "https://www.lidl.nl/assets/gcp8b70d928d56946b185437a48b4cd6b92.jpg"
  },
  {
    "n": "Stoomstrijkijzer FV2838 4/5 (37) Tefal Adviesprijs: *",
    "p": "35.99",
    "o": "",
    "s": "",
    "l": "https://www.lidl.nl/assets/gcpe160932d7b6c4e5bbbe2b58d1a9c9479.jpeg"
  },
  {
    "n": "Stoomstrijkijzer Light and Easy Brights Sapphire 3.7/5 (10) Russell Hobbs Adviesprijs: *",
    "p": "24.99",
    "o": "",
    "s": "",
    "l": "https://www.lidl.nl/assets/gcpf5e957563f7a461195284cb7b226c063.jpg"
  },
  {
    "n": "Stoomstrijkijzer Russell Hobbs Adviesprijs: *",
    "p": "9.99",
    "o": "",
    "s": "",
    "l": "https://www.lidl.nl/assets/gcp3ef9616c9d4e4252b4dbe21dafb70b23.jpg"
  },
  {
    "n": "Stoomgenerator IS1013GR BRAUN Adviesprijs: *",
    "p": "59.99",
    "o": "",
    "s": "",
    "l": "https://www.lidl.nl/assets/gcpe95a7a41c5a34d2a85c15d427a9f4bcf.jpg"
  },
  {
    "n": "Strijkpop voor overhemden PRO STEAM Cleanmaxx Adviesprijs: *",
    "p": "82.99",
    "o": "",
    "s": "",
    "l": "https://www.lidl.nl/assets/gcp0ed4f0817e6144629255f598de613d20.jpg"
  },
  {
    "n": "Kledingstomer Beldray",
    "p": "19.99",
    "o": "-42%",
    "s": "",
    "l": "https://www.lidl.nl/assets/gcpc02f7823f16b49ab812c91e64b4451e6.jpg"
  },
  {
    "n": "Stoomstrijkijzer Express Easy SV6110 1/5 (1) Tefal Adviesprijs: *",
    "p": "89.99",
    "o": "",
    "s": "",
    "l": "https://www.lidl.nl/assets/gcpbbe6a73f1df744309ce65bcadd1497b0.jpg"
  },
  {
    "n": "Stoomstrijksysteem Vaporella 505 Pro Polti",
    "p": "49.99",
    "o": "-51%",
    "s": "",
    "l": "https://www.lidl.nl/assets/gcp6ff767a2d2cd4d51bde82f20c21feabd.jpg"
  },
  {
    "n": "Prullenbak (Wit) 4.6/5 (44) LIVARNO home",
    "p": "8.99",
    "o": "",
    "s": "",
    "l": "https://www.lidl.nl/assets/gcp94e88eaee3164679bff3feac9595970f.jpg"
  },
  {
    "n": "Inbouw prullenbak 4.7/5 (14) LIVARNO home",
    "p": "59.99",
    "o": "",
    "s": "",
    "l": "https://www.lidl.nl/assets/gcp2521ce9db47e46ceb2b727212febee34.jpg"
  },
  {
    "n": "Stapelbare Recyclingbox 5/5 (2) LIVARNO home",
    "p": "7.99",
    "o": "-33%",
    "s": "",
    "l": "https://www.lidl.nl/assets/gcp91500c0f16f44bf1a7db65c42d81fdb6.jpg"
  },
  {
    "n": "Stoomreiniger Steam One XXL 4.6/5 (49) Vileda Adviesprijs: *",
    "p": "84.99",
    "o": "",
    "s": "",
    "l": "https://www.lidl.nl/assets/gcpf364131a58f1461485812835d7dd203d.jpeg"
  },
  {
    "n": "Stoomreiniger Steam ONE 4.6/5 (22) Vileda",
    "p": "69.99",
    "o": "-12%",
    "s": "",
    "l": "https://www.lidl.nl/assets/gcp51cd3bab4d1a4861bcb76ff7a48dc9be.jpeg"
  },
  {
    "n": "Handstoomreiniger 4.3/5 (227) SILVERCREST®",
    "p": "29.99",
    "o": "",
    "s": "",
    "l": "https://www.lidl.nl/assets/gcpe93ab3e56a454fad8adddecba9629c99.jpg"
  },
  {
    "n": "Kledingstomer Steamer Pro (Zwart/goud) 5/5 (2) Beldray Adviesprijs: *",
    "p": "29.99",
    "o": "",
    "s": "",
    "l": "https://www.lidl.nl/assets/gcpfc883e38ab33420391df7e9a76bbdea6.jpg"
  },
  {
    "n": "Stoomreiniger 1500 W 2/5 (2) SILVERCREST®",
    "p": "69.99",
    "o": "",
    "s": "",
    "l": "https://www.lidl.nl/assets/gcp239d54711aab47f2b5ceb05172f1aee1.jpg"
  },
  {
    "n": "Stoomreiniger Steam One XXL 4.6/5 (49) Vileda Adviesprijs: *",
    "p": "84.99",
    "o": "",
    "s": "",
    "l": "https://www.lidl.nl/assets/gcpf364131a58f1461485812835d7dd203d.jpeg"
  },
  {
    "n": "Pluizenverwijderaar 4.4/5 (60) SILVERCREST®",
    "p": "2.99",
    "o": "-50%",
    "s": "",
    "l": "https://www.lidl.nl/assets/gcp1fe9965b15d64d10983379ff2f16e6fd.jpg"
  },
  {
    "n": "Stoomreiniger Steam ONE 4.6/5 (22) Vileda",
    "p": "69.99",
    "o": "-12%",
    "s": "",
    "l": "https://www.lidl.nl/assets/gcp51cd3bab4d1a4861bcb76ff7a48dc9be.jpeg"
  },
  {
    "n": "Handstoomreiniger 4.3/5 (227) SILVERCREST®",
    "p": "29.99",
    "o": "",
    "s": "",
    "l": "https://www.lidl.nl/assets/gcpe93ab3e56a454fad8adddecba9629c99.jpg"
  },
  {
    "n": "Raamwisser met sproeifunctie 3.8/5 (16) LIVARNO home",
    "p": "14.99",
    "o": "",
    "s": "",
    "l": "https://www.lidl.nl/assets/gcp250f6a4face64b20968aa4b3858e87d3.jpg"
  },
  {
    "n": "Schoonmaakdoeken of schuursponsjes 4.7/5 (3) Vileda",
    "p": "2.99",
    "o": "Tip van Lidl",
    "s": "",
    "l": "https://www.lidl.nl/assets/gcp14c91a95125b4a3b8c4c41873847b8ed.jpeg"
  },
  {
    "n": "RVS antiroeststaaf en reinigingspasta 4.7/5 (3) ROKITTA Adviesprijs: *",
    "p": "11.99",
    "o": "RVS anti-roeststaaf en reinigingspasta RVS anti-roeststaaf en reinigingspasta",
    "s": "",
    "l": "https://www.lidl.nl/assets/gcpc824af957dbb443ebfce5aa359eb9cee.jpeg"
  },
  {
    "n": "Reservefilter CrossWave 5/5 (2) Bissell Adviesprijs: *",
    "p": "8.99",
    "o": "",
    "s": "",
    "l": "https://www.lidl.nl/assets/gcp42b8569bf24e4933849dcac242819b17.jpeg"
  },
  {
    "n": "Kledingstomer Steamer Pro (Zwart/goud) 5/5 (2) Beldray Adviesprijs: *",
    "p": "29.99",
    "o": "",
    "s": "",
    "l": "https://www.lidl.nl/assets/gcpfc883e38ab33420391df7e9a76bbdea6.jpg"
  },
  {
    "n": "Stoomreiniger 1500 W 2/5 (2) SILVERCREST®",
    "p": "69.99",
    "o": "",
    "s": "",
    "l": "https://www.lidl.nl/assets/gcp239d54711aab47f2b5ceb05172f1aee1.jpg"
  },
  {
    "n": "Pluizenverwijderaar 500 Series GCA2000/80 PHILIPS",
    "p": "14.99",
    "o": "",
    "s": "",
    "l": "https://www.lidl.nl/assets/gcpd22b3ac3b49f4077a7bdb7ba8168e355.jpg"
  },
  {
    "n": "Schrobborstelpads Bissell Adviesprijs: *",
    "p": "10.99",
    "o": "Schrobborstel-pads Schrobborstel-pads",
    "s": "",
    "l": "https://www.lidl.nl/assets/gcp722d2ac0d7bc4c2aa6af9b00f46f4448.jpeg"
  },
  {
    "n": "Softmoppads voor de SpinWave Bissell Adviesprijs: *",
    "p": "10.99",
    "o": "Soft-mop-pads voor de SpinWave Soft-mop-pads voor de SpinWave",
    "s": "",
    "l": "https://www.lidl.nl/assets/gcp9957a4670ebb4ae4a0437e6f6cd3ba12.jpeg"
  },
  {
    "n": "Borstelrol »CrossWave« voor multioppervlakreiniger Bissell Adviesprijs: *",
    "p": "10.99",
    "o": "Borstelrol »CrossWave« voor multi-oppervlakreiniger Borstelrol »CrossWave« voor multi-oppervlakreiniger",
    "s": "",
    "l": "https://www.lidl.nl/assets/gcpa3feb786c18c4a87bc7c8d83a949ebb8.jpeg"
  },
  {
    "n": "Vervangingsfilter voor Aquastar PRO kraan filtersysteem Schütte",
    "p": "71.99",
    "o": "Vervangingsfilter voor Aquastar PRO kraan filtersysteem Vervangingsfilter voor Aquastar PRO kraan filtersysteem",
    "s": "",
    "l": "https://www.lidl.nl/assets/gcpbd9ab9c2985f4be3a93220c99baf42af.jpeg"
  },
  {
    "n": "Filter voor MultiReach Essential 2280N Bissell",
    "p": "9.99",
    "o": "",
    "s": "",
    "l": "https://www.lidl.nl/assets/gcp1e10d103cab44749a85d05c200a1cd3a.jpeg"
  },
  {
    "n": "Borstelroller voor houten vloeren Bissell",
    "p": "14.99",
    "o": "",
    "s": "",
    "l": "https://www.lidl.nl/assets/gcp6ad055703ee14a7b917effc74dc61ffd.jpeg"
  },
  {
    "n": "Pluizenverwijderaar 4.4/5 (60) SILVERCREST®",
    "p": "2.99",
    "o": "-50%",
    "s": "",
    "l": "https://www.lidl.nl/assets/gcp1fe9965b15d64d10983379ff2f16e6fd.jpg"
  },
  {
    "n": "Waterbezemset 4.6/5 (26) PARKSIDE®",
    "p": "24.99",
    "o": "",
    "s": "",
    "l": "https://www.lidl.nl/assets/gcp982d99aca07b4c53b13c0b576fd36e27.jpg"
  },
  {
    "n": "Vloerwisser met sproeifunctie 4.3/5 (66) LIVARNO home",
    "p": "6.99",
    "o": "-53%",
    "s": "",
    "l": "https://www.lidl.nl/assets/gcp40ef7dd3e0a641b2b4f142372445a829.jpeg"
  },
  {
    "n": "2 reservehoezen 4.6/5 (34) LEIFHEIT Adviesprijs: *",
    "p": "16.99",
    "o": "",
    "s": "",
    "l": "https://www.lidl.nl/assets/gcpa32ad48f7a2f412a850190102391617a.jpg"
  },
  {
    "n": "Dweilset 4.3/5 (44) LEIFHEIT Adviesprijs: *",
    "p": "19.99",
    "o": "",
    "s": "",
    "l": "https://www.lidl.nl/assets/gcpfbd47e4d1d1b4e87805af5e4eaa52d30.jpeg"
  },
  {
    "n": "Dweilset Spray and Clean 4.4/5 (16) Vileda Adviesprijs: *",
    "p": "24.99",
    "o": "",
    "s": "",
    "l": "https://www.lidl.nl/assets/gcpd0815785c0ef4b6ba4087ded67de9ce0.jpeg"
  },
  {
    "n": "Veegset 4.4/5 (14) PARKSIDE®",
    "p": "7.99",
    "o": "",
    "s": "",
    "l": "https://www.lidl.nl/assets/gcpc167b78b84364fc08624ee27d49319e0.jpeg"
  },
  {
    "n": "Extra hoes Ultramax Beste beoordelingen 4.8/5 (8) Vileda",
    "p": "8.99",
    "o": "",
    "s": "",
    "l": "https://www.lidl.nl/assets/gcp153938f71da74711b4aaf3bd6cd38607.jpeg"
  },
  {
    "n": "Kärcher Accuborstel KB 5 4.2/5 (20) Adviesprijs: *",
    "p": "61.21",
    "o": "",
    "s": "",
    "l": "https://www.lidl.nl/assets/gcp743c6833fe9f4a85a5aac97b6e943566.jpeg"
  },
  {
    "n": "Raamwisser met sproeifunctie 3.8/5 (16) LIVARNO home",
    "p": "14.99",
    "o": "",
    "s": "",
    "l": "https://www.lidl.nl/assets/gcp250f6a4face64b20968aa4b3858e87d3.jpg"
  },
  {
    "n": "Microvezelhoezen Steam ONE Beste beoordelingen 5/5 (6) Vileda",
    "p": "11.99",
    "o": "",
    "s": "",
    "l": "https://www.lidl.nl/assets/gcp175fb4ae7eb74781afc4bc3f70233bdc.jpeg"
  },
  {
    "n": "Easy Wring and Clean vervangingshoes 5/5 (5) Vileda",
    "p": "5.99",
    "o": "Easy Wring and Clean vervangingshoes Easy Wring and Clean vervangingshoes",
    "s": "",
    "l": "https://www.lidl.nl/assets/gcp773f6889d2dd49a3a3bb639be488a967.jpeg"
  },
  {
    "n": "Stoffer en blik 4.6/5 (5) LIVARNO home",
    "p": "2.99",
    "o": "",
    "s": "",
    "l": "https://www.lidl.nl/assets/gcp1728fc7be57d4acc8953bc9fef83d7e3.jpg"
  },
  {
    "n": "Bezem (Straatbezem met duwplaat) 3.2/5 (19) PARKSIDE®",
    "p": "4.99",
    "o": "-50%",
    "s": "",
    "l": "https://www.lidl.nl/assets/gcp3fbf8094bcba423bbc856e8cbb3cdf9b.jpeg"
  },
  {
    "n": "Accuraamreiniger 4.5/5 (2) SILVERCREST®",
    "p": "29.99",
    "o": "Accu-raamreiniger Accu-raamreiniger",
    "s": "",
    "l": "https://www.lidl.nl/assets/gcpd6430d17e28f45b1a80997830da822dc.jpg"
  },
  {
    "n": "Schoonmaakdoeken of schuursponsjes 4.7/5 (3) Vileda",
    "p": "2.99",
    "o": "Tip van Lidl",
    "s": "",
    "l": "https://www.lidl.nl/assets/gcp14c91a95125b4a3b8c4c41873847b8ed.jpeg"
  },
  {
    "n": "Ultramax Colours dweilset (Blauw) 5/5 (2) Vileda",
    "p": "19.99",
    "o": "",
    "s": "",
    "l": "https://www.lidl.nl/assets/gcp0e34a4b25ba34698ae8e82a8f70c53a8.jpg"
  },
  {
    "n": "RVS antiroeststaaf en reinigingspasta 4.7/5 (3) ROKITTA Adviesprijs: *",
    "p": "11.99",
    "o": "RVS anti-roeststaaf en reinigingspasta RVS anti-roeststaaf en reinigingspasta",
    "s": "",
    "l": "https://www.lidl.nl/assets/gcpc824af957dbb443ebfce5aa359eb9cee.jpeg"
  },
  {
    "n": "Reservefilter CrossWave 5/5 (2) Bissell Adviesprijs: *",
    "p": "8.99",
    "o": "",
    "s": "",
    "l": "https://www.lidl.nl/assets/gcp42b8569bf24e4933849dcac242819b17.jpeg"
  },
  {
    "n": "Plat wissysteem Easy Twist 4/5 (2) Vileda",
    "p": "17.99",
    "o": "-28%",
    "s": "",
    "l": "https://www.lidl.nl/assets/gcpd6168cc0cf5b485a8d731de32ee4f032.jpg"
  },
  {
    "n": "Spray & Clean hoes 4/5 (2) Vileda",
    "p": "9.99",
    "o": "-16%",
    "s": "",
    "l": "https://www.lidl.nl/assets/gcpa2c94c0b09fd4945b6c2def79e9bae49.jpg"
  },
  {
    "n": "SuperMocio 3Action dweilset Vileda",
    "p": "9.99",
    "o": "-50%",
    "s": "",
    "l": "https://www.lidl.nl/assets/gcp5e4acb4c7fe54cefa10eca1f03319e71.jpg"
  },
  {
    "n": "14 microvezeldoeken Vileda",
    "p": "6.99",
    "o": "-46%",
    "s": "",
    "l": "https://www.lidl.nl/assets/gcp0d79a37078a24101a51f6a591b89eaae.jpg"
  },
  {
    "n": "2in1 wisser met sproeifunctie 4/5 (1) Wenko Adviesprijs: *",
    "p": "8.99",
    "o": "2-in-1 wisser met sproeifunctie 2-in-1 wisser met sproeifunctie",
    "s": "",
    "l": "https://www.lidl.nl/assets/gcp2eaaec59cc324bf8babf6ccf32b52062.jpg"
  },
  {
    "n": "Pluizenverwijderaar 500 Series GCA2000/80 PHILIPS",
    "p": "14.99",
    "o": "",
    "s": "",
    "l": "https://www.lidl.nl/assets/gcpd22b3ac3b49f4077a7bdb7ba8168e355.jpg"
  },
  {
    "n": "Bezem Vileda",
    "p": "14.99",
    "o": "",
    "s": "",
    "l": "https://www.lidl.nl/assets/gcpc319db0cab3d4f759cb5ef312eb662f2.jpeg"
  },
  {
    "n": "Spin & Clean dweilset Vileda",
    "p": "19.99",
    "o": "-33%",
    "s": "",
    "l": "https://www.lidl.nl/assets/gcpaf5b50cf7259446d9d2adadcc0686440.jpg"
  },
  {
    "n": "Dweilset Switch + Clean (dweilsysteem) LIVARNO home",
    "p": "19.99",
    "o": "",
    "s": "",
    "l": "https://www.lidl.nl/assets/gcp0262ce094edd4694a629f6ea884b48fe.jpg"
  },
  {
    "n": "Pet Pro Flip mop Vileda",
    "p": "20.64",
    "o": "",
    "s": "",
    "l": "https://www.lidl.nl/assets/gcp41c5bb08e22249b187dc73d8191dc5e0.jpg"
  },
  {
    "n": "Softmoppads voor de SpinWave Bissell Adviesprijs: *",
    "p": "10.99",
    "o": "Soft-mop-pads voor de SpinWave Soft-mop-pads voor de SpinWave",
    "s": "",
    "l": "https://www.lidl.nl/assets/gcp9957a4670ebb4ae4a0437e6f6cd3ba12.jpeg"
  },
  {
    "n": "Schrobborstelpads Bissell Adviesprijs: *",
    "p": "10.99",
    "o": "Schrobborstel-pads Schrobborstel-pads",
    "s": "",
    "l": "https://www.lidl.nl/assets/gcp722d2ac0d7bc4c2aa6af9b00f46f4448.jpeg"
  },
  {
    "n": "Borstelrol »CrossWave« voor multioppervlakreiniger Bissell Adviesprijs: *",
    "p": "10.99",
    "o": "Borstelrol »CrossWave« voor multi-oppervlakreiniger Borstelrol »CrossWave« voor multi-oppervlakreiniger",
    "s": "",
    "l": "https://www.lidl.nl/assets/gcpa3feb786c18c4a87bc7c8d83a949ebb8.jpeg"
  },
  {
    "n": "Filter voor MultiReach Essential 2280N Bissell",
    "p": "9.99",
    "o": "",
    "s": "",
    "l": "https://www.lidl.nl/assets/gcp1e10d103cab44749a85d05c200a1cd3a.jpeg"
  },
  {
    "n": "Borstelroller voor houten vloeren Bissell",
    "p": "14.99",
    "o": "",
    "s": "",
    "l": "https://www.lidl.nl/assets/gcp6ad055703ee14a7b917effc74dc61ffd.jpeg"
  },
  {
    "n": "Vervangingsfilter voor Aquastar PRO kraan filtersysteem Schütte",
    "p": "71.99",
    "o": "Vervangingsfilter voor Aquastar PRO kraan filtersysteem Vervangingsfilter voor Aquastar PRO kraan filtersysteem",
    "s": "",
    "l": "https://www.lidl.nl/assets/gcpbd9ab9c2985f4be3a93220c99baf42af.jpeg"
  },
  {
    "n": "Boodschappenmand (Blauw) Beste beoordelingen 4.9/5 (120) TOPMOVE®",
    "p": "11.99",
    "o": "",
    "s": "",
    "l": "https://www.lidl.nl/assets/gcp920e7335c3954970a2258e8eaf5e08d4.jpg"
  },
  {
    "n": "Thermowinkelmandje 4.7/5 (75) TOPMOVE®",
    "p": "11.99",
    "o": "Thermo-winkelmandje Thermo-winkelmandje",
    "s": "",
    "l": "https://www.lidl.nl/assets/gcpfa5583087e39450497d2d347d40a3074.jpeg"
  },
  {
    "n": "Boodschappenmandje (Blauw) Beste beoordelingen 4.8/5 (142) TOPMOVE®",
    "p": "9.99",
    "o": "",
    "s": "",
    "l": "https://www.lidl.nl/assets/gcpa4d13aec0b8549eab76ab393b03094b9.jpeg"
  },
  {
    "n": "Inklapbare boodschappentrolley 4.2/5 (49) TOPMOVE®",
    "p": "11.99",
    "o": "",
    "s": "",
    "l": "https://www.lidl.nl/assets/gcp64429d549e5e45d9b09c7af251fcb655.jpg"
  },
  {
    "n": "Boodschappentrolley 40 4.8/5 (5) TOPMOVE®",
    "p": "49.99",
    "o": "",
    "s": "40 L",
    "l": "https://www.lidl.nl/assets/gcpf6e0a09413234df28c16e5d5b2762e37.jpeg"
  },
  {
    "n": "Boodschappentassen 5/5 (2) TOPMOVE®",
    "p": "14.99",
    "o": "",
    "s": "",
    "l": "https://www.lidl.nl/assets/gcpf521c5a34ae542b688d880f0f0e54b7b.jpg"
  },
  {
    "n": "Boodschappenmand TOPMOVE® -25% Ook in de winkel",
    "p": "8.99",
    "o": "-25% Ook in de winkel 14/05 - 21/05",
    "s": "",
    "l": "https://www.lidl.nl/assets/gcpf328723dcf8949aca8fe49f3efb6824b.jpg"
  },
  {
    "n": "Vloerkleed Monroe 4.5/5 (108) Arte Espina",
    "p": "38.98",
    "o": "vanaf",
    "s": "",
    "l": "https://www.lidl.nl/assets/gcp8e0fa4a12fc54e44b9dd3ac374a34c71.jpeg"
  },
  {
    "n": "Trapmattenset 15 4.3/5 (19) LIVARNO home",
    "p": "19.99",
    "o": "",
    "s": "15 STUKS",
    "l": "https://www.lidl.nl/assets/gcp1aa294111ada4d8586073f6718e333a9.jpg"
  },
  {
    "n": "Tapijt imitatiebont 60 x 90 cm Beste beoordelingen 5/5 (7) LIVARNO home -20%",
    "p": "7.99",
    "o": "Tapijt van imitatiebont 60 x 90 cm Tapijt van imitatiebont 60 x 90 cm -20%",
    "s": "60 X 90 CM BESTE BEOORDELINGEN 5/5 (7) LIVARNO HOME TAPIJT VAN IMITATIEBONT 60 X 90 CM 9.99 -20% 7.99",
    "l": "https://www.lidl.nl/assets/gcp5e4c3f1021814ace9b31692b481e58b2.jpg"
  },
  {
    "n": "Juten tapijt 4/5 (2) LIVARNO home",
    "p": "9.99",
    "o": "-50%",
    "s": "",
    "l": "https://www.lidl.nl/assets/gcp007db96c675a4973ad1594ecf78fa389.jpg"
  },
  {
    "n": "Vloerkleed Ø100 cm 5/5 (4) LIVARNO home",
    "p": "14.99",
    "o": "",
    "s": "",
    "l": "https://www.lidl.nl/assets/gcp16a4bab108e54ef09afb1f28cc0f4c49.jpeg"
  },
  {
    "n": "Vloerkleed Rabbit Prime 5/5 (4) me gusta",
    "p": "49.99",
    "o": "vanaf Adviesprijs: vanaf 65.- *",
    "s": "",
    "l": "https://www.lidl.nl/assets/gcpfbfbce1acb3140759854cb93219a3dde.jpeg"
  },
  {
    "n": "Kortpolig tapijt 4.8/5 (5)",
    "p": "8.99",
    "o": "Tip van Lidl",
    "s": "",
    "l": "https://www.lidl.nl/assets/gcp9d1060b574024c3995a32187da343515.jpeg"
  },
  {
    "n": "Deurmat 5/5 (1) LIVARNO home",
    "p": "4.99",
    "o": "",
    "s": "",
    "l": "https://www.lidl.nl/assets/gcp8d2be48bce954c19ab7756ba71d0d774.jpg"
  },
  {
    "n": "Keukenloper 65 x 180 cm 4.8/5 (4) LIVARNO home",
    "p": "9.99",
    "o": "-50%",
    "s": "65 X 180 CM 4.8/5 (4) LIVARNO HOME KEUKENLOPER 65 X 180 CM 19.99 -50% 9.99",
    "l": "https://www.lidl.nl/assets/gcp0edfa5db0d594bd69e602011ec83f3f4.jpg"
  },
  {
    "n": "Vloerkleed 80 x 150 cm (Lichtgrijs) 4.3/5 (6) LIVARNO home",
    "p": "29.99",
    "o": "Tip van Lidl",
    "s": "80 X 150 CM (LICHTGRIJS) TIP VAN LIDL 4.3/5 (6) LIVARNO HOME VLOERKLEED 80 X 150 CM (LICHTGRIJS) 29.99",
    "l": "https://www.lidl.nl/assets/gcp670bb26fc712493bacf6e11ab1468b94.jpg"
  },
  {
    "n": "Katoenen vloerkleed 140 x 200 cm 3.1/5 (17) LIVARNO home",
    "p": "22.99",
    "o": "-42%",
    "s": "140 X 200 CM 3.1/5 (17) LIVARNO HOME KATOENEN VLOERKLEED 140 X 200 CM 39.99 -42% 22.99",
    "l": "https://www.lidl.nl/assets/gcpd1d951046e224bbfa20abd724e507bac.jpeg"
  },
  {
    "n": "Speelkleed 70 x 120 cm (Dieren) 4.5/5 (4) LIVARNO home",
    "p": "7.99",
    "o": "-33%",
    "s": "70 X 120 CM (DIEREN) 4.5/5 (4) LIVARNO HOME SPEELKLEED 70 X 120 CM (DIEREN) 11.99 -33% 7.99",
    "l": "https://www.lidl.nl/assets/gcpb0a7948d359f4dbfa342c38383360575.jpeg"
  },
  {
    "n": "Deurmat 4.5/5 (2) LIVARNO home",
    "p": "11.99",
    "o": "",
    "s": "",
    "l": "https://www.lidl.nl/assets/gcpd942830e7fe64b018d5a2a6c82d05550.jpg"
  },
  {
    "n": "Vloerkleed 2.5/5 (4) LIVARNO home",
    "p": "9.99",
    "o": "",
    "s": "",
    "l": "https://www.lidl.nl/assets/gcp8a8975b0d47041c3b6acd1399af081c1.jpg"
  },
  {
    "n": "Texels Wol Vloerkleed 90 x 60 cm 5/5 (1) TXL Comfort",
    "p": "79.95",
    "o": "",
    "s": "90 X 60 CM 5/5 (1) TXL COMFORT TEXELS WOL VLOERKLEED 90 X 60 CM 79.95",
    "l": "https://www.lidl.nl/assets/gcp9d1c3fb685ff4489a213bc60b05e1715.jpeg"
  },
  {
    "n": "Juten tapijt 5/5 (1) LIVARNO home",
    "p": "21.99",
    "o": "",
    "s": "",
    "l": "https://www.lidl.nl/assets/gcp22fc0bc31dd7434c87d5bb90ce944534.jpeg"
  },
  {
    "n": "Hoogpolig tapijt (Donkergrijs) 5/5 (1) LIVARNO home",
    "p": "15.99",
    "o": "-20%",
    "s": "",
    "l": "https://www.lidl.nl/assets/gcpde21d4b8685c4f858e67ab5feeeacc65.jpeg"
  },
  {
    "n": "Kindervloerkleed Playground Tip Lidl 5/5 (1) Arte Espina vanaf Adviesprijs: 79.- *",
    "p": "36.99",
    "o": "Tip van Lidl vanaf Adviesprijs: vanaf 79.- *",
    "s": "",
    "l": "https://www.lidl.nl/assets/gcp98506be9605a48a2940286d925701b15.jpeg"
  },
  {
    "n": "Vloerkleed Cocktail 5/5 (1) me gusta",
    "p": "29.99",
    "o": "vanaf Adviesprijs: vanaf 79.- *",
    "s": "",
    "l": "https://www.lidl.nl/assets/gcp438142bf59cd4407938ad1b48ec2b23d.jpg"
  },
  {
    "n": "Draaitapijt 80 x 160 cm 3/5 (2) LIVARNO home",
    "p": "39.99",
    "o": "",
    "s": "80 X 160 CM 3/5 (2) LIVARNO HOME DRAAITAPIJT 80 X 160 CM 39.99",
    "l": "https://www.lidl.nl/assets/gcpaf7b366152e74e3787a882d7daa867ee.jpeg"
  },
  {
    "n": "Vloerkleed Imala 3/5 (1) Padiro",
    "p": "44.99",
    "o": "vanaf Adviesprijs: vanaf 65.- *",
    "s": "",
    "l": "https://www.lidl.nl/assets/gcp789df3f1b8be4ade8fc0ce11330712ba.jpg"
  },
  {
    "n": "Vuilvangmat 3/5 (1) LIVARNO home -46%",
    "p": "6.99",
    "o": "Vuilvangmat Vuilvangmat -46%",
    "s": "",
    "l": "https://www.lidl.nl/assets/gcpe9889b66fda44b219869032ef3aedc6d.jpg"
  },
  {
    "n": "Kokos deurmat LIVARNO home",
    "p": "2.99",
    "o": "",
    "s": "",
    "l": "https://www.lidl.nl/assets/gcpc830d9e4eab64e84810e71688b9ce80b.jpg"
  },
  {
    "n": "Katoenen vloerkleed 120 x 180 cm 2/5 (2) LIVARNO home",
    "p": "37.99",
    "o": "",
    "s": "120 X 180 CM 2/5 (2) LIVARNO HOME KATOENEN VLOERKLEED 120 X 180 CM 37.99",
    "l": "https://www.lidl.nl/assets/gcp816c88ebd66d42ac838af45434dcdf90.jpeg"
  },
  {
    "n": "Vloerkleed Charme Padiro",
    "p": "68.98",
    "o": "vanaf Adviesprijs: vanaf 125.- *",
    "s": "",
    "l": "https://www.lidl.nl/assets/gcpe71d7e653d284c888f4eb3481d70cf44.jpg"
  },
  {
    "n": "Vloerkleed 80 x 150 cm LIVARNO home",
    "p": "8.99",
    "o": "-35%",
    "s": "80 X 150 CM LIVARNO HOME VLOERKLEED 80 X 150 CM 13.99 -35% 8.99",
    "l": "https://www.lidl.nl/assets/gcp3493e488b118495cb5f69bccc54b198c.jpg"
  },
  {
    "n": "Vloerkleed Madita (Grijs, 80 x 150 cm, 225) Tip Lidl KAYOOM Adviesprijs: 75.- *",
    "p": "59.99",
    "o": "Tip van Lidl Adviesprijs: 75.- *",
    "s": "80 X 150 CM, 225) TIP VAN LIDL KAYOOM VLOERKLEED MADITA (GRIJS, 80 X 150 CM, 225) ADVIESPRIJS: 75.- * 59.99",
    "l": "https://www.lidl.nl/assets/gcp9db19c9b8071481a991dd5b3043e130c.jpeg"
  },
  {
    "n": "Vloerkleed Raika Tip Lidl KAYOOM vanaf Adviesprijs: 109.- *",
    "p": "69.99",
    "o": "Tip van Lidl vanaf Adviesprijs: vanaf 109.- *",
    "s": "",
    "l": "https://www.lidl.nl/assets/gcp2930c29ff831457f99161ef5c2849faa.jpeg"
  },
  {
    "n": "Tapijtloper LIVARNO home",
    "p": "19.99",
    "o": "",
    "s": "",
    "l": "https://www.lidl.nl/assets/gcp115b98fc2c154ccda4270ed8dc1be63a.jpg"
  },
  {
    "n": "Vloerkleed Hailey Padiro",
    "p": "44.99",
    "o": "vanaf Adviesprijs: vanaf 65.- *",
    "s": "",
    "l": "https://www.lidl.nl/assets/gcp0f861750ba104e19827a7fc94c5e8c11.jpg"
  },
  {
    "n": "Kindervloerkleed Coco Arte Espina",
    "p": "59.99",
    "o": "Tip van Lidl",
    "s": "",
    "l": "https://www.lidl.nl/assets/gcp6a76b879ff65479dba115e7c7522181a.jpeg"
  },
  {
    "n": "Premium CashmereFeeling deken Beste beoordelingen 4.8/5 (736) Gözze vanaf",
    "p": "34.14",
    "o": "Premium Cashmere-Feeling deken Premium Cashmere-Feeling deken vanaf",
    "s": "",
    "l": "https://www.lidl.nl/assets/8e12876c8f42cf80747fdb8d36bf30f9.jpeg"
  },
  {
    "n": "Kussen Beste beoordelingen 4.9/5 (141) Gözze",
    "p": "17.47",
    "o": "vanaf",
    "s": "",
    "l": "https://www.lidl.nl/assets/b3eabbc770eab1bb139c5a6edd3a2ce6.jpeg"
  },
  {
    "n": "Dierenmand 4.5/5 (54) zoofari®",
    "p": "14.99",
    "o": "",
    "s": "",
    "l": "https://www.lidl.nl/assets/gcpa039c23d7a0d422e9dfad31727e097ab.jpg"
  },
  {
    "n": "Baby knuffeldeken, 70 x 100 cm (Lichtgrijs) 4.6/5 (24) bellybutton Adviesprijs: *",
    "p": "16.99",
    "o": "",
    "s": "70 X 100 CM (LICHTGRIJS) 4.6/5 (24) BELLYBUTTON BABY KNUFFELDEKEN, 70 X 100 CM (LICHTGRIJS) ADVIESPRIJS: 59.95 * 16.99",
    "l": "https://www.lidl.nl/assets/gcpce03968d80a14ae7bf1e8dff2fbf805a.jpeg"
  },
  {
    "n": "Kussenhoes MINK Beste beoordelingen 4.9/5 (12) MAGMA",
    "p": "19.99",
    "o": "",
    "s": "",
    "l": "https://www.lidl.nl/assets/c74658a9323f91f3988d92e8df7af15a.jpeg"
  },
  {
    "n": "Kussenhoes NOBLESS (Groen) Beste beoordelingen 4.8/5 (13) MAGMA Adviesprijs: *",
    "p": "9.99",
    "o": "",
    "s": "",
    "l": "https://www.lidl.nl/assets/04fcdb7c93b8acc76e83474004b0ed86.jpeg"
  },
  {
    "n": "Woondeken 200 x 220 cm 5/5 (5) LIVARNO home",
    "p": "19.99",
    "o": "",
    "s": "200 X 220 CM 5/5 (5) LIVARNO HOME WOONDEKEN 200 X 220 CM 19.99",
    "l": "https://www.lidl.nl/assets/gcp03e41513c0b34ed5aebb8af5443f7857.jpeg"
  },
  {
    "n": "Plaid 150 x 200 cm 5/5 (5) LIVARNO home",
    "p": "14.99",
    "o": "-25%",
    "s": "150 X 200 CM 5/5 (5) LIVARNO HOME PLAID 150 X 200 CM 19.99 -25% 14.99",
    "l": "https://www.lidl.nl/assets/gcpb19b247dfd9c4b0da01b13759fde6bb4.jpg"
  },
  {
    "n": "Picknickkleed 125 x 160 cm 4.3/5 (7)",
    "p": "8.99",
    "o": "",
    "s": "125 X 160 CM 4.3/5 (7) PICKNICKKLEED 125 X 160 CM 8.99",
    "l": "https://www.lidl.nl/assets/gcp23e937e596114d58ad1bd6bdfad3fb2a.jpeg"
  },
  {
    "n": "Teddy fleecedeken 150 x 200 cm 3.7/5 (11) LIVARNO home",
    "p": "20.99",
    "o": "",
    "s": "150 X 200 CM 3.7/5 (11) LIVARNO HOME TEDDY FLEECEDEKEN 150 X 200 CM 20.99",
    "l": "https://www.lidl.nl/assets/gcp88f629574d784c6f86434cfa68c24062.jpeg"
  },
  {
    "n": "Plaid 150 x 200 cm 5/5 (3) SANSIBAR",
    "p": "29.99",
    "o": "",
    "s": "150 X 200 CM 5/5 (3) SANSIBAR PLAID 150 X 200 CM 29.99",
    "l": "https://www.lidl.nl/assets/gcp5fca990ed1c94ea2b2f524597419285f.jpg"
  },
  {
    "n": "Kussenhoes TAIMA 4.2/5 (5) MAGMA",
    "p": "17.99",
    "o": "",
    "s": "",
    "l": "https://www.lidl.nl/assets/6edb4ea1499c70fee6d1183ef1b88690.jpeg"
  },
  {
    "n": "Kussenhoes MONKEY 4.7/5 (3) MAGMA",
    "p": "21.99",
    "o": "vanaf",
    "s": "",
    "l": "https://www.lidl.nl/assets/e167d31696a6c96c68d995822077491c.jpeg"
  },
  {
    "n": "Accuwarmtedeken 2.8/5 (13) SANITAS",
    "p": "49.99",
    "o": "Accu-warmtedeken Accu-warmtedeken",
    "s": "",
    "l": "https://www.lidl.nl/assets/gcpb28dd47c572c4ee2ba122ef73450b61b.jpg"
  },
  {
    "n": "Deken voor kinderen 5/5 (2) LIVARNO home",
    "p": "5.99",
    "o": "",
    "s": "",
    "l": "https://www.lidl.nl/assets/gcp6b60152b6aaf493c99f5baf664ee7c3e.jpg"
  },
  {
    "n": "Plaid 125 x 140 cm 3.7/5 (3) LIVARNO home",
    "p": "9.99",
    "o": "-23%",
    "s": "125 X 140 CM 3.7/5 (3) LIVARNO HOME PLAID 125 X 140 CM 12.99 -23% 9.99",
    "l": "https://www.lidl.nl/assets/gcp2de77266ca744169840865cf30abe8c0.jpeg"
  },
  {
    "n": "Plaid 200 x 220 cm LIVARNO home",
    "p": "5.99",
    "o": "-50%",
    "s": "200 X 220 CM LIVARNO HOME PLAID 200 X 220 CM 11.99 -50% 5.99",
    "l": "https://www.lidl.nl/assets/gcpd7b7701c723c4028a456694a4350d6a3.jpg"
  },
  {
    "n": "Decoratiekussen 60 x 90 cm 3.7/5 (3) LIVARNO home",
    "p": "17.99",
    "o": "",
    "s": "60 X 90 CM 3.7/5 (3) LIVARNO HOME DECORATIEKUSSEN 60 X 90 CM 17.99",
    "l": "https://www.lidl.nl/assets/gcp18768744068e428baae7df0bbf4c51b3.jpeg"
  },
  {
    "n": "Plaid 130 x 170 cm 3/5 (5) LIVARNO home",
    "p": "6.99",
    "o": "",
    "s": "130 X 170 CM 3/5 (5) LIVARNO HOME PLAID 130 X 170 CM 6.99",
    "l": "https://www.lidl.nl/assets/gcp0553aabba5974eb0900346bf81208777.jpg"
  },
  {
    "n": "Sprei met ruches LIVARNO home",
    "p": "17.99",
    "o": "",
    "s": "",
    "l": "https://www.lidl.nl/assets/gcp17154a22053846b3be46cc2bedd1bb55.jpg"
  },
  {
    "n": "Plaid 150 x 200 cm 5/5 (1) LIVARNO home",
    "p": "5.99",
    "o": "-50%",
    "s": "150 X 200 CM 5/5 (1) LIVARNO HOME PLAID 150 X 200 CM 11.99 -50% 5.99",
    "l": "https://www.lidl.nl/assets/gcp98fe88c2d2ac46c189ffa72a0039ac1d.jpg"
  },
  {
    "n": "Kussenhoes ZEBRA 5/5 (1) MAGMA",
    "p": "18.99",
    "o": "vanaf",
    "s": "",
    "l": "https://www.lidl.nl/assets/e2928b4c1393222bef3458bc6ac434ae.jpeg"
  },
  {
    "n": "Kussenhoes OYO 3.5/5 (2) MAGMA",
    "p": "21.99",
    "o": "",
    "s": "",
    "l": "https://www.lidl.nl/assets/2d3b75695dedde787266c27a84267ffd.jpeg"
  },
  {
    "n": "Woondeken MAGMA",
    "p": "49.90",
    "o": "",
    "s": "",
    "l": "https://www.lidl.nl/assets/5bbd4ddd84826055477735f557e5c2aa.jpeg"
  },
  {
    "n": "Plaid 130 x 170 cm LIVARNO home",
    "p": "5.99",
    "o": "",
    "s": "130 X 170 CM LIVARNO HOME PLAID 130 X 170 CM 5.99",
    "l": "https://www.lidl.nl/assets/gcp552b185b6be1490d83dca6a9b3e6922e.jpg"
  },
  {
    "n": "Plaid 180 x 240 cm LIVARNO home",
    "p": "24.99",
    "o": "",
    "s": "180 X 240 CM LIVARNO HOME PLAID 180 X 240 CM 24.99",
    "l": "https://www.lidl.nl/assets/gcpedbed477d7e64e699f08c1806fcd6190.jpg"
  },
  {
    "n": "Plaid 150 x 250 cm LIVARNO home",
    "p": "13.99",
    "o": "",
    "s": "150 X 250 CM LIVARNO HOME PLAID 150 X 250 CM 13.99",
    "l": "https://www.lidl.nl/assets/gcp2d0aa7d04aa84537b8182e5fc9aa567e.jpg"
  },
  {
    "n": "Kussen 50 x cm LIVARNO home",
    "p": "12.99",
    "o": "",
    "s": "50 X 50 CM LIVARNO HOME KUSSEN 50 X 50 CM 12.99",
    "l": "https://www.lidl.nl/assets/gcpf9cb7e7e4c8a4cca8d360c847421c51d.jpg"
  },
  {
    "n": "Tafelkleed of tafelloper Beste beoordelingen 4.8/5 (6) LIVARNO home",
    "p": "9.99",
    "o": "",
    "s": "",
    "l": "https://www.lidl.nl/assets/gcp2ea8ff98400e4a40a69586221cc0b310.jpeg"
  },
  {
    "n": "Tafelkleed & tafelloper set LIVARNO home",
    "p": "9.99",
    "o": "",
    "s": "",
    "l": "https://www.lidl.nl/assets/gcp72700829b53a43d985dd1175245e176e.jpg"
  },
  {
    "n": "Tafelkleed of -lopers LIVARNO home Ook in de winkel",
    "p": "5.99",
    "o": "Tafelkleed of -lopers Tafelkleed of -lopers Ook in de winkel 14/05 - 21/05",
    "s": "",
    "l": "https://www.lidl.nl/assets/gcp5c8ccf0b29fd454ba4ef0432781974bb.jpg"
  },
  {
    "n": "Tuintafelkleed 130 x 160 cm LIVARNO home",
    "p": "14.99",
    "o": "",
    "s": "130 X 160 CM LIVARNO HOME TUINTAFELKLEED 130 X 160 CM 14.99",
    "l": "https://www.lidl.nl/assets/gcp22f54ac7b2b64cb1955db7a96140e782.jpg"
  },
  {
    "n": "Tafelkleed LIVARNO home",
    "p": "4.99",
    "o": "",
    "s": "",
    "l": "https://www.lidl.nl/assets/gcp7ab4ed27229e4cc2984493007b25d771.jpg"
  },
  {
    "n": "Tafelkleed 140 x 240 cm LIVARNO home",
    "p": "19.99",
    "o": "",
    "s": "140 X 240 CM LIVARNO HOME TAFELKLEED 140 X 240 CM 19.99",
    "l": "https://www.lidl.nl/assets/gcp4c8973a73e454fe8993cf9a5063a3508.jpg"
  }
]